{"version": 0.6, "generator": "Overpass API 0.7.62.7 375dc00a", "osm3s": {"timestamp_osm_base": "2025-07-22T15:26:40Z", "copyright": "The data included in this document is from www.openstreetmap.org. The data is made available under ODbL."}, "elements": [{"type": "node", "id": 336765601, "lat": 6.4430326, "lon": -75.3272484}, {"type": "node", "id": 336765604, "lat": 6.4415848, "lon": -75.3320364}, {"type": "node", "id": 336765606, "lat": 6.4380196, "lon": -75.3338751}, {"type": "node", "id": 1397149007, "lat": 6.4429965, "lon": -75.3273698}, {"type": "node", "id": 1397149009, "lat": 6.4431485, "lon": -75.3270821}, {"type": "node", "id": 1397149011, "lat": 6.4428793, "lon": -75.328494}, {"type": "node", "id": 1397149013, "lat": 6.4429305, "lon": -75.3278894}, {"type": "node", "id": 1397149019, "lat": 6.4427714, "lon": -75.3290731}, {"type": "node", "id": 1397149020, "lat": 6.4426546, "lon": -75.3294955}, {"type": "node", "id": 1397149165, "lat": 6.4425371, "lon": -75.3297391}, {"type": "node", "id": 1397149173, "lat": 6.4423704, "lon": -75.3299296}, {"type": "node", "id": 1397149177, "lat": 6.4419091, "lon": -75.3304785}, {"type": "node", "id": 1397149184, "lat": 6.441319, "lon": -75.3324032}, {"type": "node", "id": 1397149185, "lat": 6.4417207, "lon": -75.3309209}, {"type": "node", "id": 1397149192, "lat": 6.4414791, "lon": -75.3323099}, {"type": "node", "id": 1397149194, "lat": 6.4418354, "lon": -75.3306011}, {"type": "node", "id": 1397149225, "lat": 6.4353795, "lon": -75.3362703}, {"type": "node", "id": 1397149227, "lat": 6.4364196, "lon": -75.335324}, {"type": "node", "id": 2186616496, "lat": 6.422889, "lon": -75.320555}, {"type": "node", "id": 2186616503, "lat": 6.4228641, "lon": -75.3206335}, {"type": "node", "id": 2186616511, "lat": 6.42289, "lon": -75.32079}, {"type": "node", "id": 2186616518, "lat": 6.423359, "lon": -75.321517}, {"type": "node", "id": 2186616519, "lat": 6.423369, "lon": -75.321456}, {"type": "node", "id": 2186616521, "lat": 6.422925, "lon": -75.320859}, {"type": "node", "id": 2186616523, "lat": 6.423232, "lon": -75.321779}, {"type": "node", "id": 2186616525, "lat": 6.423355, "lon": -75.321383}, {"type": "node", "id": 2186616526, "lat": 6.423068, "lon": -75.321077}, {"type": "node", "id": 2186616532, "lat": 6.423224, "lon": -75.321849}, {"type": "node", "id": 2186616542, "lat": 6.423726, "lon": -75.323}, {"type": "node", "id": 2186616543, "lat": 6.423676, "lon": -75.323073}, {"type": "node", "id": 2186616549, "lat": 6.424065, "lon": -75.322792}, {"type": "node", "id": 2186616552, "lat": 6.42367, "lon": -75.323138}, {"type": "node", "id": 2186616554, "lat": 6.423246, "lon": -75.321921}, {"type": "node", "id": 2186616567, "lat": 6.423693, "lon": -75.323204}, {"type": "node", "id": 2186616568, "lat": 6.42417, "lon": -75.322698}, {"type": "node", "id": 2186616569, "lat": 6.423292, "lon": -75.32197}, {"type": "node", "id": 2186616574, "lat": 6.423353, "lon": -75.322004}, {"type": "node", "id": 2186616575, "lat": 6.423745, "lon": -75.323276}, {"type": "node", "id": 2186616576, "lat": 6.424201, "lon": -75.322636}, {"type": "node", "id": 2186616582, "lat": 6.423585, "lon": -75.322058}, {"type": "node", "id": 2186616583, "lat": 6.424205, "lon": -75.322543}, {"type": "node", "id": 2186616585, "lat": 6.423824, "lon": -75.323332}, {"type": "node", "id": 2186616587, "lat": 6.42426, "lon": -75.324645}, {"type": "node", "id": 2186616588, "lat": 6.424271, "lon": -75.324742}, {"type": "node", "id": 2186616589, "lat": 6.424161, "lon": -75.323345}, {"type": "node", "id": 2186616591, "lat": 6.424327, "lon": -75.324036}, {"type": "node", "id": 2186616592, "lat": 6.423733, "lon": -75.322113}, {"type": "node", "id": 2186616593, "lat": 6.424171, "lon": -75.322474}, {"type": "node", "id": 2186616596, "lat": 6.424111, "lon": -75.322418}, {"type": "node", "id": 2186616597, "lat": 6.423891, "lon": -75.323349}, {"type": "node", "id": 2186616599, "lat": 6.424075, "lon": -75.323329}, {"type": "node", "id": 2186616600, "lat": 6.424225, "lon": -75.323388}, {"type": "node", "id": 2186616601, "lat": 6.424284, "lon": -75.323494}, {"type": "node", "id": 2186616606, "lat": 6.424351, "lon": -75.324853}, {"type": "node", "id": 2186616613, "lat": 6.424437, "lon": -75.324898}, {"type": "node", "id": 2186616614, "lat": 6.424587, "lon": -75.326441}, {"type": "node", "id": 2186616615, "lat": 6.424577, "lon": -75.32652}, {"type": "node", "id": 2186616620, "lat": 6.424638, "lon": -75.326281}, {"type": "node", "id": 2186616621, "lat": 6.424616, "lon": -75.326773}, {"type": "node", "id": 2186616622, "lat": 6.424496, "lon": -75.324907}, {"type": "node", "id": 2186616623, "lat": 6.424762, "lon": -75.326114}, {"type": "node", "id": 2186616627, "lat": 6.424751, "lon": -75.325316}, {"type": "node", "id": 2186616628, "lat": 6.424803, "lon": -75.32545}, {"type": "node", "id": 2186616629, "lat": 6.424699, "lon": -75.326911}, {"type": "node", "id": 2186616631, "lat": 6.424892, "lon": -75.326067}, {"type": "node", "id": 2186616632, "lat": 6.42483, "lon": -75.325162}, {"type": "node", "id": 2186616633, "lat": 6.424755, "lon": -75.324769}, {"type": "node", "id": 2186616636, "lat": 6.42489, "lon": -75.325525}, {"type": "node", "id": 2186616638, "lat": 6.42513, "lon": -75.326042}, {"type": "node", "id": 2186616640, "lat": 6.425379, "lon": -75.325073}, {"type": "node", "id": 2186616641, "lat": 6.424841, "lon": -75.324724}, {"type": "node", "id": 2186616642, "lat": 6.424759, "lon": -75.326947}, {"type": "node", "id": 2186616647, "lat": 6.425447, "lon": -75.325035}, {"type": "node", "id": 2186616651, "lat": 6.425234, "lon": -75.325717}, {"type": "node", "id": 2186616652, "lat": 6.425017, "lon": -75.327034}, {"type": "node", "id": 2186616653, "lat": 6.425214, "lon": -75.32602}, {"type": "node", "id": 2186616656, "lat": 6.424952, "lon": -75.324706}, {"type": "node", "id": 2186616657, "lat": 6.425322, "lon": -75.325858}, {"type": "node", "id": 2186616658, "lat": 6.425258, "lon": -75.325995}, {"type": "node", "id": 2186616659, "lat": 6.425492, "lon": -75.324982}, {"type": "node", "id": 2186616665, "lat": 6.4253904, "lon": -75.3274651}, {"type": "node", "id": 2186616666, "lat": 6.425147, "lon": -75.327127}, {"type": "node", "id": 2186616668, "lat": 6.42551, "lon": -75.3249}, {"type": "node", "id": 2186616673, "lat": 6.425419, "lon": -75.324798}, {"type": "node", "id": 2186616675, "lat": 6.425478, "lon": -75.324834}, {"type": "node", "id": 2186616683, "lat": 6.425233, "lon": -75.327217}, {"type": "node", "id": 2186616686, "lat": 6.424353, "lon": -75.32865}, {"type": "node", "id": 2186616687, "lat": 6.424439, "lon": -75.328647}, {"type": "node", "id": 2186616688, "lat": 6.424699, "lon": -75.328596}, {"type": "node", "id": 2186616689, "lat": 6.424839, "lon": -75.328605}, {"type": "node", "id": 2186616690, "lat": 6.425436, "lon": -75.328796}, {"type": "node", "id": 2186616691, "lat": 6.425327, "lon": -75.328721}, {"type": "node", "id": 2186616692, "lat": 6.425484, "lon": -75.328859}, {"type": "node", "id": 2186616693, "lat": 6.425558, "lon": -75.329107}, {"type": "node", "id": 2186616694, "lat": 6.425782, "lon": -75.329523}, {"type": "node", "id": 2186616697, "lat": 6.425853, "lon": -75.329627}, {"type": "node", "id": 2186616698, "lat": 6.425924, "lon": -75.329692}, {"type": "node", "id": 2186616699, "lat": 6.426057, "lon": -75.329729}, {"type": "node", "id": 2186616702, "lat": 6.425996, "lon": -75.329721}, {"type": "node", "id": 2186616703, "lat": 6.426373, "lon": -75.329689}, {"type": "node", "id": 2186616704, "lat": 6.426569, "lon": -75.329685}, {"type": "node", "id": 2186616705, "lat": 6.426648, "lon": -75.329668}, {"type": "node", "id": 2186616709, "lat": 6.4268112, "lon": -75.3290549}, {"type": "node", "id": 2186616714, "lat": 6.427553, "lon": -75.3285875}, {"type": "node", "id": 2186616717, "lat": 6.427905, "lon": -75.329639}, {"type": "node", "id": 2186616719, "lat": 6.427832, "lon": -75.329573}, {"type": "node", "id": 2186616720, "lat": 6.4276002, "lon": -75.3286493}, {"type": "node", "id": 2186616726, "lat": 6.4276152, "lon": -75.3287113}, {"type": "node", "id": 2186616727, "lat": 6.427651, "lon": -75.329043}, {"type": "node", "id": 2186616728, "lat": 6.4282639, "lon": -75.3295968}, {"type": "node", "id": 2186616735, "lat": 6.4283105, "lon": -75.3296248}, {"type": "node", "id": 2186616738, "lat": 6.4283863, "lon": -75.3297515}, {"type": "node", "id": 2186616739, "lat": 6.4283282, "lon": -75.3299382}, {"type": "node", "id": 2186616741, "lat": 6.428336, "lon": -75.330021}, {"type": "node", "id": 2186616744, "lat": 6.428369, "lon": -75.330074}, {"type": "node", "id": 2186616745, "lat": 6.428615, "lon": -75.330339}, {"type": "node", "id": 2186616750, "lat": 6.428746, "lon": -75.330557}, {"type": "node", "id": 2186616753, "lat": 6.428841, "lon": -75.330663}, {"type": "node", "id": 2186616755, "lat": 6.429043, "lon": -75.330948}, {"type": "node", "id": 2186616760, "lat": 6.429133, "lon": -75.331011}, {"type": "node", "id": 2186616763, "lat": 6.429189, "lon": -75.33103}, {"type": "node", "id": 2186616767, "lat": 6.429414, "lon": -75.330936}, {"type": "node", "id": 2186616768, "lat": 6.429291, "lon": -75.331026}, {"type": "node", "id": 2186616770, "lat": 6.429368, "lon": -75.330986}, {"type": "node", "id": 2186616773, "lat": 6.429828, "lon": -75.330946}, {"type": "node", "id": 2186616776, "lat": 6.429903, "lon": -75.331078}, {"type": "node", "id": 2186616783, "lat": 6.430106, "lon": -75.331262}, {"type": "node", "id": 2186616786, "lat": 6.430197, "lon": -75.331369}, {"type": "node", "id": 2186616787, "lat": 6.430531, "lon": -75.331976}, {"type": "node", "id": 2186616790, "lat": 6.430349, "lon": -75.331699}, {"type": "node", "id": 2186616791, "lat": 6.430547, "lon": -75.332108}, {"type": "node", "id": 2186616793, "lat": 6.430578, "lon": -75.335957}, {"type": "node", "id": 2186616794, "lat": 6.430513, "lon": -75.336081}, {"type": "node", "id": 2186616795, "lat": 6.430534, "lon": -75.332213}, {"type": "node", "id": 2186616796, "lat": 6.430666, "lon": -75.335875}, {"type": "node", "id": 2186616801, "lat": 6.430489, "lon": -75.332378}, {"type": "node", "id": 2186616802, "lat": 6.431089, "lon": -75.335781}, {"type": "node", "id": 2186616803, "lat": 6.430488, "lon": -75.332439}, {"type": "node", "id": 2186616807, "lat": 6.430647, "lon": -75.332773}, {"type": "node", "id": 2186616808, "lat": 6.430733, "lon": -75.333064}, {"type": "node", "id": 2186616809, "lat": 6.430781, "lon": -75.333137}, {"type": "node", "id": 2186616810, "lat": 6.431193, "lon": -75.335703}, {"type": "node", "id": 2186616811, "lat": 6.430828, "lon": -75.333172}, {"type": "node", "id": 2186616812, "lat": 6.431222, "lon": -75.335345}, {"type": "node", "id": 2186616813, "lat": 6.430926, "lon": -75.333188}, {"type": "node", "id": 2186616814, "lat": 6.431507, "lon": -75.335136}, {"type": "node", "id": 2186616815, "lat": 6.431243, "lon": -75.335271}, {"type": "node", "id": 2186616816, "lat": 6.43163, "lon": -75.334973}, {"type": "node", "id": 2186616817, "lat": 6.431323, "lon": -75.335196}, {"type": "node", "id": 2186616818, "lat": 6.431661, "lon": -75.334835}, {"type": "node", "id": 2186616820, "lat": 6.431003, "lon": -75.333159}, {"type": "node", "id": 2186616821, "lat": 6.431722, "lon": -75.33471}, {"type": "node", "id": 2186616822, "lat": 6.431337, "lon": -75.332832}, {"type": "node", "id": 2186616823, "lat": 6.431799, "lon": -75.334626}, {"type": "node", "id": 2186616824, "lat": 6.431972, "lon": -75.334507}, {"type": "node", "id": 2186616825, "lat": 6.432253, "lon": -75.334342}, {"type": "node", "id": 2186616826, "lat": 6.432325, "lon": -75.334264}, {"type": "node", "id": 2186616827, "lat": 6.43254, "lon": -75.333985}, {"type": "node", "id": 2186616828, "lat": 6.431462, "lon": -75.332732}, {"type": "node", "id": 2186616831, "lat": 6.432565, "lon": -75.333924}, {"type": "node", "id": 2186616832, "lat": 6.431707, "lon": -75.332575}, {"type": "node", "id": 2186616833, "lat": 6.431816, "lon": -75.332551}, {"type": "node", "id": 2186616834, "lat": 6.431888, "lon": -75.332571}, {"type": "node", "id": 2186616835, "lat": 6.431941, "lon": -75.33261}, {"type": "node", "id": 2186616836, "lat": 6.432557, "lon": -75.333819}, {"type": "node", "id": 2186616837, "lat": 6.432024, "lon": -75.332756}, {"type": "node", "id": 2186616839, "lat": 6.432532, "lon": -75.333732}, {"type": "node", "id": 2186616840, "lat": 6.432054, "lon": -75.332885}, {"type": "node", "id": 2186616841, "lat": 6.432499, "lon": -75.33366}, {"type": "node", "id": 2186616842, "lat": 6.432063, "lon": -75.333088}, {"type": "node", "id": 2186616843, "lat": 6.432456, "lon": -75.333606}, {"type": "node", "id": 2186616844, "lat": 6.432112, "lon": -75.333238}, {"type": "node", "id": 2186616845, "lat": 6.432083, "lon": -75.333187}, {"type": "node", "id": 2186616862, "lat": 6.4423138, "lon": -75.3319901}, {"type": "node", "id": 2186616865, "lat": 6.4440171, "lon": -75.331756}, {"type": "node", "id": 2186616868, "lat": 6.4453886, "lon": -75.331643}, {"type": "node", "id": 3474224952, "lat": 6.441113, "lon": -75.3325018}, {"type": "node", "id": 3474224954, "lat": 6.4414143, "lon": -75.3324316}, {"type": "node", "id": 3474224955, "lat": 6.4414219, "lon": -75.3324748}, {"type": "node", "id": 3474224956, "lat": 6.4414392, "lon": -75.3323486}, {"type": "node", "id": 3474224957, "lat": 6.4414423, "lon": -75.3325135}, {"type": "node", "id": 3474224958, "lat": 6.4414735, "lon": -75.3325442}, {"type": "node", "id": 3474224959, "lat": 6.4415237, "lon": -75.3322912}, {"type": "node", "id": 3474224960, "lat": 6.4415125, "lon": -75.3325637}, {"type": "node", "id": 3474224961, "lat": 6.4415719, "lon": -75.3322887}, {"type": "node", "id": 3474224962, "lat": 6.4415891, "lon": -75.3325659}, {"type": "node", "id": 3474224963, "lat": 6.4416181, "lon": -75.3323029}, {"type": "node", "id": 3474224964, "lat": 6.441625, "lon": -75.3325512}, {"type": "node", "id": 3474224965, "lat": 6.4416555, "lon": -75.3325272}, {"type": "node", "id": 3474224966, "lat": 6.4416638, "lon": -75.3323401}, {"type": "node", "id": 3474224967, "lat": 6.441685, "lon": -75.3323764}, {"type": "node", "id": 3474224968, "lat": 6.4416917, "lon": -75.3324593}, {"type": "node", "id": 3474224969, "lat": 6.4416783, "lon": -75.3324958}, {"type": "node", "id": 3474224970, "lat": 6.4417704, "lon": -75.3307357}, {"type": "node", "id": 3474224971, "lat": 6.4420373, "lon": -75.3321191}, {"type": "node", "id": 3474224972, "lat": 6.4426181, "lon": -75.3319046}, {"type": "node", "id": 3745182525, "lat": 6.430709, "lon": -75.336503}, {"type": "node", "id": 3745182526, "lat": 6.430541, "lon": -75.336286}, {"type": "node", "id": 3745182527, "lat": 6.430514, "lon": -75.336222}, {"type": "node", "id": 3745182528, "lat": 6.430539, "lon": -75.336016}, {"type": "node", "id": 3745182529, "lat": 6.430744, "lon": -75.335837}, {"type": "node", "id": 3745182530, "lat": 6.431223, "lon": -75.335633}, {"type": "node", "id": 3745182531, "lat": 6.431568, "lon": -75.335089}, {"type": "node", "id": 3745182537, "lat": 6.432359, "lon": -75.333516}, {"type": "node", "id": 3745182538, "lat": 6.430504, "lon": -75.33191}, {"type": "node", "id": 3745182539, "lat": 6.429749, "lon": -75.330675}, {"type": "node", "id": 3745182540, "lat": 6.429711, "lon": -75.330618}, {"type": "node", "id": 3745182541, "lat": 6.429648, "lon": -75.330584}, {"type": "node", "id": 3745182542, "lat": 6.429589, "lon": -75.330598}, {"type": "node", "id": 3745182543, "lat": 6.42952, "lon": -75.330687}, {"type": "node", "id": 3745182544, "lat": 6.4281831, "lon": -75.3295796}, {"type": "node", "id": 3745182545, "lat": 6.4280203, "lon": -75.3296559}, {"type": "node", "id": 3745182546, "lat": 6.4274518, "lon": -75.328549}, {"type": "node", "id": 3745182547, "lat": 6.4273883, "lon": -75.3285587}, {"type": "node", "id": 3745182548, "lat": 6.4273057, "lon": -75.3286222}, {"type": "node", "id": 3745182549, "lat": 6.427217, "lon": -75.328727}, {"type": "node", "id": 3745182550, "lat": 6.427169, "lon": -75.328793}, {"type": "node", "id": 3745182551, "lat": 6.4268496, "lon": -75.3289879}, {"type": "node", "id": 3745182552, "lat": 6.4267998, "lon": -75.3291246}, {"type": "node", "id": 3745182553, "lat": 6.426799, "lon": -75.32936}, {"type": "node", "id": 3745182554, "lat": 6.426759, "lon": -75.329576}, {"type": "node", "id": 3745182555, "lat": 6.426724, "lon": -75.329623}, {"type": "node", "id": 3745182556, "lat": 6.424254, "lon": -75.328615}, {"type": "node", "id": 3745182557, "lat": 6.424213, "lon": -75.328581}, {"type": "node", "id": 3745182558, "lat": 6.424172, "lon": -75.328506}, {"type": "node", "id": 3745182559, "lat": 6.424168, "lon": -75.328357}, {"type": "node", "id": 3745182560, "lat": 6.424208, "lon": -75.328269}, {"type": "node", "id": 3745182561, "lat": 6.424267, "lon": -75.32822}, {"type": "node", "id": 3745182562, "lat": 6.424538, "lon": -75.328108}, {"type": "node", "id": 3745182563, "lat": 6.425271, "lon": -75.327871}, {"type": "node", "id": 3745182564, "lat": 6.425328, "lon": -75.327832}, {"type": "node", "id": 3745182565, "lat": 6.425404, "lon": -75.327747}, {"type": "node", "id": 3745182566, "lat": 6.425434, "lon": -75.327668}, {"type": "node", "id": 3745182567, "lat": 6.425435, "lon": -75.327597}, {"type": "node", "id": 3745182583, "lat": 6.424653, "lon": -75.326861}, {"type": "node", "id": 3745182584, "lat": 6.425302, "lon": -75.325942}, {"type": "node", "id": 3745182585, "lat": 6.425286, "lon": -75.325763}, {"type": "node", "id": 3745182586, "lat": 6.424761, "lon": -75.325265}, {"type": "node", "id": 3745182587, "lat": 6.424936, "lon": -75.325104}, {"type": "node", "id": 3745182588, "lat": 6.425248, "lon": -75.325092}, {"type": "node", "id": 3745182589, "lat": 6.424627, "lon": -75.324867}, {"type": "node", "id": 3745182590, "lat": 6.424297, "lon": -75.324796}, {"type": "node", "id": 3745182591, "lat": 6.427051, "lon": -75.32887}, {"type": "node", "id": 3745182592, "lat": 6.4269173, "lon": -75.3289359}, {"type": "node", "id": 3745182593, "lat": 6.426786, "lon": -75.329502}, {"type": "node", "id": 3745182594, "lat": 6.424587, "lon": -75.326643}, {"type": "node", "id": 3745182595, "lat": 6.424705, "lon": -75.326167}, {"type": "node", "id": 3745182596, "lat": 6.424763, "lon": -75.325384}, {"type": "node", "id": 3745182597, "lat": 6.424322, "lon": -75.324278}, {"type": "node", "id": 3745182598, "lat": 6.424322, "lon": -75.323839}, {"type": "node", "id": 3745182615, "lat": 6.42383, "lon": -75.322172}, {"type": "node", "id": 3782066930, "lat": 6.436469, "lon": -75.3313335}, {"type": "node", "id": 3782066940, "lat": 6.4383349, "lon": -75.3336555}, {"type": "node", "id": 3782066942, "lat": 6.439398, "lon": -75.3332016}, {"type": "node", "id": 3937925164, "lat": 6.435837, "lon": -75.3358595}, {"type": "node", "id": 4074260166, "lat": 6.4373031, "lon": -75.3192107}, {"type": "node", "id": 4235522204, "lat": 6.4400906, "lon": -75.3297801}, {"type": "node", "id": 4235522208, "lat": 6.438762, "lon": -75.333478}, {"type": "node", "id": 4548737069, "lat": 6.4358241, "lon": -75.3338252}, {"type": "node", "id": 4548737070, "lat": 6.4357778, "lon": -75.3338732}, {"type": "node", "id": 4548737071, "lat": 6.4354147, "lon": -75.3334166}, {"type": "node", "id": 4548737072, "lat": 6.4367072, "lon": -75.3350636}, {"type": "node", "id": 4548737073, "lat": 6.4367704, "lon": -75.3350063}, {"type": "node", "id": 4548737076, "lat": 6.4428071, "lon": -75.3289138}, {"type": "node", "id": 4548737077, "lat": 6.4416912, "lon": -75.3311644}, {"type": "node", "id": 4548737078, "lat": 6.4416409, "lon": -75.331564}, {"type": "node", "id": 4548737079, "lat": 6.4409431, "lon": -75.3325703}, {"type": "node", "id": 4548737080, "lat": 6.4413804, "lon": -75.3312449}, {"type": "node", "id": 4548737082, "lat": 6.441173, "lon": -75.3309332}, {"type": "node", "id": 4548737083, "lat": 6.4409429, "lon": -75.3306881}, {"type": "node", "id": 4548737084, "lat": 6.4402871, "lon": -75.3299895}, {"type": "node", "id": 4548737085, "lat": 6.4405078, "lon": -75.3302246}, {"type": "node", "id": 4548737086, "lat": 6.440711, "lon": -75.3304411}, {"type": "node", "id": 4548737088, "lat": 6.4397698, "lon": -75.3330565}, {"type": "node", "id": 4548737389, "lat": 6.436569, "lon": -75.3341705}, {"type": "node", "id": 4548737391, "lat": 6.4364245, "lon": -75.3340256}, {"type": "node", "id": 4548737392, "lat": 6.4366903, "lon": -75.334292}, {"type": "node", "id": 4548737393, "lat": 6.4366193, "lon": -75.3351432}, {"type": "node", "id": 4548737394, "lat": 6.436323, "lon": -75.3354119}, {"type": "node", "id": 4548737395, "lat": 6.4383145, "lon": -75.333847}, {"type": "node", "id": 4548737396, "lat": 6.4379, "lon": -75.3339834}, {"type": "node", "id": 4548737397, "lat": 6.4376865, "lon": -75.3341768}, {"type": "node", "id": 4548737398, "lat": 6.4377636, "lon": -75.334107}, {"type": "node", "id": 4548737399, "lat": 6.434551, "lon": -75.3370036}, {"type": "node", "id": 4548737400, "lat": 6.4349942, "lon": -75.3366113}, {"type": "node", "id": 4548737401, "lat": 6.4349109, "lon": -75.336685}, {"type": "node", "id": 4548737403, "lat": 6.4382292, "lon": -75.3337165}, {"type": "node", "id": 4548737404, "lat": 6.4383255, "lon": -75.3336589}, {"type": "node", "id": 4548737405, "lat": 6.4367286, "lon": -75.3311996}, {"type": "node", "id": 4548737406, "lat": 6.4306154, "lon": -75.3257364}, {"type": "node", "id": 4548737407, "lat": 6.4357473, "lon": -75.3359339}, {"type": "node", "id": 4548737408, "lat": 6.4357676, "lon": -75.3358943}, {"type": "node", "id": 4548737409, "lat": 6.4358119, "lon": -75.3357724}, {"type": "node", "id": 4548737410, "lat": 6.4358325, "lon": -75.3355438}, {"type": "node", "id": 4548737411, "lat": 6.4360061, "lon": -75.3318501}, {"type": "node", "id": 4548737412, "lat": 6.4360435, "lon": -75.3305487}, {"type": "node", "id": 4548737446, "lat": 6.4407738, "lon": -75.3318726}, {"type": "node", "id": 4548737447, "lat": 6.4406905, "lon": -75.3319576}, {"type": "node", "id": 4548737448, "lat": 6.4404639, "lon": -75.3316498}, {"type": "node", "id": 4548737449, "lat": 6.4402231, "lon": -75.3314106}, {"type": "node", "id": 4548737450, "lat": 6.4397755, "lon": -75.3309407}, {"type": "node", "id": 4548737451, "lat": 6.4407943, "lon": -75.332202}, {"type": "node", "id": 4548737452, "lat": 6.4395664, "lon": -75.3309234}, {"type": "node", "id": 4548737453, "lat": 6.4398988, "lon": -75.3312696}, {"type": "node", "id": 4548737454, "lat": 6.4400733, "lon": -75.3314512}, {"type": "node", "id": 4548737455, "lat": 6.4401915, "lon": -75.3315744}, {"type": "node", "id": 4548737456, "lat": 6.4403424, "lon": -75.3317314}, {"type": "node", "id": 4548737457, "lat": 6.440443, "lon": -75.3318362}, {"type": "node", "id": 4548737458, "lat": 6.440581, "lon": -75.3319799}, {"type": "node", "id": 4548737459, "lat": 6.4407308, "lon": -75.3321359}, {"type": "node", "id": 4548737460, "lat": 6.4391575, "lon": -75.3313095}, {"type": "node", "id": 4548737461, "lat": 6.4394722, "lon": -75.3316536}, {"type": "node", "id": 4548737462, "lat": 6.4396435, "lon": -75.3318398}, {"type": "node", "id": 4548737463, "lat": 6.4397559, "lon": -75.3319629}, {"type": "node", "id": 4548737464, "lat": 6.4399029, "lon": -75.3321231}, {"type": "node", "id": 4548737465, "lat": 6.4400073, "lon": -75.3322371}, {"type": "node", "id": 4548737466, "lat": 6.4401523, "lon": -75.3323997}, {"type": "node", "id": 4548737467, "lat": 6.4402416, "lon": -75.3325801}, {"type": "node", "id": 4548737468, "lat": 6.439983, "lon": -75.332828}, {"type": "node", "id": 4548737469, "lat": 6.43981, "lon": -75.3327094}, {"type": "node", "id": 4548737470, "lat": 6.4396506, "lon": -75.3325511}, {"type": "node", "id": 4548737471, "lat": 6.4395352, "lon": -75.332438}, {"type": "node", "id": 4548737472, "lat": 6.4393806, "lon": -75.3322863}, {"type": "node", "id": 4548737473, "lat": 6.4392639, "lon": -75.3321717}, {"type": "node", "id": 4548737474, "lat": 6.4390885, "lon": -75.3319991}, {"type": "node", "id": 4548737475, "lat": 6.4387633, "lon": -75.3316817}, {"type": "node", "id": 4548737476, "lat": 6.4393041, "lon": -75.3330735}, {"type": "node", "id": 4548737477, "lat": 6.4391914, "lon": -75.3329625}, {"type": "node", "id": 4548737478, "lat": 6.4390692, "lon": -75.3328422}, {"type": "node", "id": 4548737479, "lat": 6.438916, "lon": -75.3326912}, {"type": "node", "id": 4548737480, "lat": 6.4388025, "lon": -75.3325797}, {"type": "node", "id": 4548737481, "lat": 6.4386312, "lon": -75.3324109}, {"type": "node", "id": 4548737482, "lat": 6.4383175, "lon": -75.3321025}, {"type": "node", "id": 4548737483, "lat": 6.4384736, "lon": -75.3330426}, {"type": "node", "id": 4548737484, "lat": 6.4382714, "lon": -75.3327349}, {"type": "node", "id": 4548737486, "lat": 6.4380877, "lon": -75.3332986}, {"type": "node", "id": 4548737487, "lat": 6.4379229, "lon": -75.3330486}, {"type": "node", "id": 4548737488, "lat": 6.4376848, "lon": -75.33269}, {"type": "node", "id": 4548737489, "lat": 6.4370561, "lon": -75.331735}, {"type": "node", "id": 4548737490, "lat": 6.4388635, "lon": -75.3346865}, {"type": "node", "id": 4548737491, "lat": 6.4395926, "lon": -75.3352901}, {"type": "node", "id": 4548737492, "lat": 6.4376094, "lon": -75.3327642}, {"type": "node", "id": 4548737493, "lat": 6.4385909, "lon": -75.3349638}, {"type": "node", "id": 4548737494, "lat": 6.4375677, "lon": -75.333526}, {"type": "node", "id": 4548737495, "lat": 6.4374257, "lon": -75.3333304}, {"type": "node", "id": 4548737500, "lat": 6.4367212, "lon": -75.3336372}, {"type": "node", "id": 4548737503, "lat": 6.436402, "lon": -75.3339511}, {"type": "node", "id": 4548737504, "lat": 6.4352241, "lon": -75.3355256}, {"type": "node", "id": 4548737505, "lat": 6.4347026, "lon": -75.3365925}, {"type": "node", "id": 4548737506, "lat": 6.4348862, "lon": -75.3364291}, {"type": "node", "id": 4548737507, "lat": 6.4350989, "lon": -75.3362399}, {"type": "node", "id": 4548737508, "lat": 6.4353354, "lon": -75.3360295}, {"type": "node", "id": 4548737509, "lat": 6.4355455, "lon": -75.3358364}, {"type": "node", "id": 4548737510, "lat": 6.43274, "lon": -75.3298488}, {"type": "node", "id": 4548737511, "lat": 6.4326766, "lon": -75.3270624}, {"type": "node", "id": 4548737512, "lat": 6.432811, "lon": -75.3263938}, {"type": "node", "id": 4548737513, "lat": 6.4338206, "lon": -75.3260417}, {"type": "node", "id": 4548737514, "lat": 6.4334365, "lon": -75.3267722}, {"type": "node", "id": 4548737516, "lat": 6.4340041, "lon": -75.3268177}, {"type": "node", "id": 4548737517, "lat": 6.4342096, "lon": -75.3277789}, {"type": "node", "id": 4548737518, "lat": 6.4352114, "lon": -75.3281417}, {"type": "node", "id": 4548737519, "lat": 6.4361124, "lon": -75.3283921}, {"type": "node", "id": 4548737520, "lat": 6.435767, "lon": -75.3287419}, {"type": "node", "id": 4548737521, "lat": 6.4353146, "lon": -75.3291987}, {"type": "node", "id": 4548737522, "lat": 6.4348576, "lon": -75.3296605}, {"type": "node", "id": 4548737523, "lat": 6.4346666, "lon": -75.3318041}, {"type": "node", "id": 4548737524, "lat": 6.435008, "lon": -75.3316433}, {"type": "node", "id": 4548737525, "lat": 6.4352771, "lon": -75.3306528}, {"type": "node", "id": 4548737526, "lat": 6.4350223, "lon": -75.3303755}, {"type": "node", "id": 4548737527, "lat": 6.4352804, "lon": -75.3301125}, {"type": "node", "id": 4548737528, "lat": 6.4357533, "lon": -75.3296305}, {"type": "node", "id": 4548737529, "lat": 6.4362043, "lon": -75.3291709}, {"type": "node", "id": 4548737530, "lat": 6.4365583, "lon": -75.3288105}, {"type": "node", "id": 4548737531, "lat": 6.4371566, "lon": -75.3293719}, {"type": "node", "id": 4548737532, "lat": 6.436797, "lon": -75.3297523}, {"type": "node", "id": 4548737533, "lat": 6.4363532, "lon": -75.3302213}, {"type": "node", "id": 4548737534, "lat": 6.4374064, "lon": -75.3303499}, {"type": "node", "id": 4548737535, "lat": 6.4377855, "lon": -75.3299621}, {"type": "node", "id": 4548737536, "lat": 6.4384782, "lon": -75.3306121}, {"type": "node", "id": 4548737537, "lat": 6.4379638, "lon": -75.3308967}, {"type": "node", "id": 4548737538, "lat": 6.4375021, "lon": -75.331326}, {"type": "node", "id": 4548737539, "lat": 6.4369778, "lon": -75.331804}, {"type": "node", "id": 4548737540, "lat": 6.4364474, "lon": -75.3322937}, {"type": "node", "id": 4548737541, "lat": 6.4359397, "lon": -75.3327623}, {"type": "node", "id": 4548737542, "lat": 6.4354603, "lon": -75.3332048}, {"type": "node", "id": 4548737543, "lat": 6.4354845, "lon": -75.3330383}, {"type": "node", "id": 4548737544, "lat": 6.4355575, "lon": -75.3331151}, {"type": "node", "id": 4548737548, "lat": 6.4358464, "lon": -75.3348566}, {"type": "node", "id": 4548737549, "lat": 6.4357953, "lon": -75.3353666}, {"type": "node", "id": 4548737550, "lat": 6.4357153, "lon": -75.3351703}, {"type": "node", "id": 4548737551, "lat": 6.4356623, "lon": -75.3350119}, {"type": "node", "id": 4548737552, "lat": 6.4355908, "lon": -75.3347418}, {"type": "node", "id": 4548737553, "lat": 6.4355445, "lon": -75.3342464}, {"type": "node", "id": 4548737554, "lat": 6.4357574, "lon": -75.3338909}, {"type": "node", "id": 4548737555, "lat": 6.4360395, "lon": -75.3336225}, {"type": "node", "id": 4548737556, "lat": 6.4364163, "lon": -75.3332679}, {"type": "node", "id": 4548737557, "lat": 6.4369394, "lon": -75.3327755}, {"type": "node", "id": 4548737558, "lat": 6.4373571, "lon": -75.3323824}, {"type": "node", "id": 4548737559, "lat": 6.4374351, "lon": -75.3323099}, {"type": "node", "id": 4548737560, "lat": 6.4379888, "lon": -75.3317785}, {"type": "node", "id": 4548737561, "lat": 6.4384308, "lon": -75.3313544}, {"type": "node", "id": 4548737562, "lat": 6.4388396, "lon": -75.330962}, {"type": "node", "id": 4548737563, "lat": 6.4369528, "lon": -75.3308115}, {"type": "node", "id": 4548737564, "lat": 6.4390134, "lon": -75.3297694}, {"type": "node", "id": 4548737578, "lat": 6.4369116, "lon": -75.3277012}, {"type": "node", "id": 4548737580, "lat": 6.4402179, "lon": -75.3296704}, {"type": "node", "id": 4548737581, "lat": 6.4401833, "lon": -75.3297016}, {"type": "node", "id": 4548737582, "lat": 6.4400438, "lon": -75.3292383}, {"type": "node", "id": 4548737583, "lat": 6.4411915, "lon": -75.3287424}, {"type": "node", "id": 4548737584, "lat": 6.4411271, "lon": -75.3287904}, {"type": "node", "id": 4548737585, "lat": 6.4410244, "lon": -75.3288686}, {"type": "node", "id": 4548737586, "lat": 6.4408677, "lon": -75.3290039}, {"type": "node", "id": 4548737587, "lat": 6.4405679, "lon": -75.3286903}, {"type": "node", "id": 4548737588, "lat": 6.4406732, "lon": -75.328475}, {"type": "node", "id": 4548737589, "lat": 6.4409632, "lon": -75.3281705}, {"type": "node", "id": 4548737590, "lat": 6.4416417, "lon": -75.3283156}, {"type": "node", "id": 4548737591, "lat": 6.4423979, "lon": -75.3289602}, {"type": "node", "id": 4548737592, "lat": 6.4426107, "lon": -75.3273412}, {"type": "node", "id": 4548737593, "lat": 6.4428251, "lon": -75.3273493}, {"type": "node", "id": 4548737594, "lat": 6.4393392, "lon": -75.3304826}, {"type": "node", "id": 4548737595, "lat": 6.4392371, "lon": -75.3305806}, {"type": "node", "id": 4548737660, "lat": 6.441604, "lon": -75.3312411}, {"type": "node", "id": 4548737661, "lat": 6.441552, "lon": -75.3312599}, {"type": "node", "id": 4548737662, "lat": 6.4415487, "lon": -75.3313539}, {"type": "node", "id": 4548737663, "lat": 6.4414988, "lon": -75.3312952}, {"type": "node", "id": 4548737664, "lat": 6.4414631, "lon": -75.3312629}, {"type": "node", "id": 4548737665, "lat": 6.4411939, "lon": -75.3311683}, {"type": "node", "id": 4548737666, "lat": 6.4411753, "lon": -75.3320149}, {"type": "node", "id": 4548737667, "lat": 6.441143, "lon": -75.331952}, {"type": "node", "id": 4548737668, "lat": 6.4383011, "lon": -75.333622}, {"type": "node", "id": 4548737776, "lat": 6.441118, "lon": -75.336135}, {"type": "node", "id": 4548737777, "lat": 6.440618, "lon": -75.335862}, {"type": "node", "id": 4548737778, "lat": 6.439293, "lon": -75.335123}, {"type": "node", "id": 4548737779, "lat": 6.439077, "lon": -75.334952}, {"type": "node", "id": 4548737780, "lat": 6.438928, "lon": -75.334785}, {"type": "node", "id": 4548737782, "lat": 6.4392433, "lon": -75.3356241}, {"type": "node", "id": 4548737786, "lat": 6.439974, "lon": -75.3294599}, {"type": "node", "id": 4548737787, "lat": 6.439851, "lon": -75.3293669}, {"type": "node", "id": 4548737804, "lat": 6.442365, "lon": -75.3278123}, {"type": "node", "id": 4548737821, "lat": 6.4425783, "lon": -75.3276887}, {"type": "node", "id": 4548737822, "lat": 6.4424677, "lon": -75.3279454}, {"type": "node", "id": 4548737824, "lat": 6.442541, "lon": -75.3273272}, {"type": "node", "id": 4548737825, "lat": 6.442431, "lon": -75.3272622}, {"type": "node", "id": 4548737826, "lat": 6.442374, "lon": -75.3271592}, {"type": "node", "id": 4548737856, "lat": 6.440046, "lon": -75.329478}, {"type": "node", "id": 4548737857, "lat": 6.440022, "lon": -75.329367}, {"type": "node", "id": 4548737860, "lat": 6.434662, "lon": -75.3275043}, {"type": "node", "id": 4548737865, "lat": 6.4341815, "lon": -75.3280831}, {"type": "node", "id": 4548737866, "lat": 6.4344107, "lon": -75.3273765}, {"type": "node", "id": 4548737867, "lat": 6.434166, "lon": -75.3271364}, {"type": "node", "id": 4548737868, "lat": 6.4339743, "lon": -75.3267018}, {"type": "node", "id": 4548737869, "lat": 6.433898, "lon": -75.326195}, {"type": "node", "id": 4548737870, "lat": 6.4333613, "lon": -75.3268163}, {"type": "node", "id": 4548737871, "lat": 6.4333169, "lon": -75.3268246}, {"type": "node", "id": 4548737872, "lat": 6.432443, "lon": -75.326023}, {"type": "node", "id": 4548737873, "lat": 6.4334997, "lon": -75.3268494}, {"type": "node", "id": 4548737874, "lat": 6.4329975, "lon": -75.3262796}, {"type": "node", "id": 4548737875, "lat": 6.432686, "lon": -75.326675}, {"type": "node", "id": 4548737876, "lat": 6.4325107, "lon": -75.3268135}, {"type": "node", "id": 4548737877, "lat": 6.433491, "lon": -75.327945}, {"type": "node", "id": 4548737879, "lat": 6.4329759, "lon": -75.3279186}, {"type": "node", "id": 4548737880, "lat": 6.4328409, "lon": -75.3277328}, {"type": "node", "id": 4548737881, "lat": 6.432794, "lon": -75.32768}, {"type": "node", "id": 4548737882, "lat": 6.432755, "lon": -75.327668}, {"type": "node", "id": 4548737883, "lat": 6.432504, "lon": -75.327653}, {"type": "node", "id": 4548737884, "lat": 6.432491, "lon": -75.327626}, {"type": "node", "id": 4548737885, "lat": 6.432504, "lon": -75.327578}, {"type": "node", "id": 4548737886, "lat": 6.4326309, "lon": -75.3274686}, {"type": "node", "id": 4548737887, "lat": 6.4326646, "lon": -75.3274255}, {"type": "node", "id": 4548737888, "lat": 6.43268, "lon": -75.327151}, {"type": "node", "id": 4548737889, "lat": 6.4326539, "lon": -75.3269984}, {"type": "node", "id": 4548737890, "lat": 6.4310278, "lon": -75.3259168}, {"type": "node", "id": 4548737891, "lat": 6.4308433, "lon": -75.3258365}, {"type": "node", "id": 4548737894, "lat": 6.4358553, "lon": -75.3307477}, {"type": "node", "id": 4548737895, "lat": 6.435233, "lon": -75.330059}, {"type": "node", "id": 4548737896, "lat": 6.434633, "lon": -75.329422}, {"type": "node", "id": 4548737897, "lat": 6.434404, "lon": -75.329197}, {"type": "node", "id": 4548737898, "lat": 6.4341157, "lon": -75.3289976}, {"type": "node", "id": 4548737899, "lat": 6.433939, "lon": -75.328598}, {"type": "node", "id": 4548737900, "lat": 6.433857, "lon": -75.328411}, {"type": "node", "id": 4548737901, "lat": 6.4336632, "lon": -75.328049}, {"type": "node", "id": 4548737902, "lat": 6.4336322, "lon": -75.3279887}, {"type": "node", "id": 4548737904, "lat": 6.4333812, "lon": -75.3280125}, {"type": "node", "id": 4548737905, "lat": 6.433267, "lon": -75.3280369}, {"type": "node", "id": 4548737906, "lat": 6.432191, "lon": -75.327945}, {"type": "node", "id": 4548737907, "lat": 6.4309512, "lon": -75.3276502}, {"type": "node", "id": 4548737908, "lat": 6.4307121, "lon": -75.3276715}, {"type": "node", "id": 4548737909, "lat": 6.430206, "lon": -75.3275569}, {"type": "node", "id": 4548737910, "lat": 6.429896, "lon": -75.327735}, {"type": "node", "id": 4548737911, "lat": 6.429601, "lon": -75.328509}, {"type": "node", "id": 4548737912, "lat": 6.4297563, "lon": -75.3281016}, {"type": "node", "id": 4548737917, "lat": 6.432095, "lon": -75.32916}, {"type": "node", "id": 4548737918, "lat": 6.431792, "lon": -75.329082}, {"type": "node", "id": 4548737919, "lat": 6.431691, "lon": -75.328999}, {"type": "node", "id": 4548737920, "lat": 6.432301, "lon": -75.329257}, {"type": "node", "id": 4548737921, "lat": 6.4322971, "lon": -75.3292194}, {"type": "node", "id": 4548737922, "lat": 6.43231, "lon": -75.3291695}, {"type": "node", "id": 4548737923, "lat": 6.4322727, "lon": -75.3291278}, {"type": "node", "id": 4548737924, "lat": 6.4322376, "lon": -75.3291276}, {"type": "node", "id": 4548737925, "lat": 6.4322112, "lon": -75.3291458}, {"type": "node", "id": 4548737926, "lat": 6.432209, "lon": -75.329197}, {"type": "node", "id": 4548737927, "lat": 6.432086, "lon": -75.329365}, {"type": "node", "id": 4548737928, "lat": 6.4318347, "lon": -75.3294522}, {"type": "node", "id": 4548737929, "lat": 6.431698, "lon": -75.32991}, {"type": "node", "id": 4548737930, "lat": 6.4326912, "lon": -75.3289227}, {"type": "node", "id": 4548737931, "lat": 6.4325, "lon": -75.329051}, {"type": "node", "id": 4548737932, "lat": 6.4324077, "lon": -75.329178}, {"type": "node", "id": 4548737933, "lat": 6.4323583, "lon": -75.3292597}, {"type": "node", "id": 4548737934, "lat": 6.432347, "lon": -75.329327}, {"type": "node", "id": 4548737935, "lat": 6.4322097, "lon": -75.3296504}, {"type": "node", "id": 4548737936, "lat": 6.432199, "lon": -75.3299028}, {"type": "node", "id": 4548737937, "lat": 6.431928, "lon": -75.330466}, {"type": "node", "id": 4548737942, "lat": 6.432514, "lon": -75.33051}, {"type": "node", "id": 4548737943, "lat": 6.432441, "lon": -75.330325}, {"type": "node", "id": 4548737944, "lat": 6.432442, "lon": -75.330242}, {"type": "node", "id": 4548737945, "lat": 6.432493, "lon": -75.330082}, {"type": "node", "id": 4548737946, "lat": 6.43261, "lon": -75.329948}, {"type": "node", "id": 4548737947, "lat": 6.432902, "lon": -75.329725}, {"type": "node", "id": 4548737948, "lat": 6.433034, "lon": -75.329478}, {"type": "node", "id": 4548737949, "lat": 6.433082, "lon": -75.32929}, {"type": "node", "id": 4548737950, "lat": 6.433073, "lon": -75.329166}, {"type": "node", "id": 4548737951, "lat": 6.432995, "lon": -75.329056}, {"type": "node", "id": 4548737952, "lat": 6.432871, "lon": -75.329016}, {"type": "node", "id": 4548737953, "lat": 6.432783, "lon": -75.329026}, {"type": "node", "id": 4548737954, "lat": 6.4326565, "lon": -75.3291316}, {"type": "node", "id": 4548737955, "lat": 6.432636, "lon": -75.3291391}, {"type": "node", "id": 4548737956, "lat": 6.4326109, "lon": -75.3291311}, {"type": "node", "id": 4548737957, "lat": 6.4325976, "lon": -75.3291105}, {"type": "node", "id": 4548737958, "lat": 6.4326143, "lon": -75.3290693}, {"type": "node", "id": 4548737959, "lat": 6.4328923, "lon": -75.3288092}, {"type": "node", "id": 4548737960, "lat": 6.4331907, "lon": -75.3287337}, {"type": "node", "id": 4548737961, "lat": 6.433417, "lon": -75.328746}, {"type": "node", "id": 4548737962, "lat": 6.433547, "lon": -75.328815}, {"type": "node", "id": 4548737963, "lat": 6.4336743, "lon": -75.3289432}, {"type": "node", "id": 4548737964, "lat": 6.4337643, "lon": -75.3290791}, {"type": "node", "id": 4548737965, "lat": 6.4339948, "lon": -75.3294952}, {"type": "node", "id": 4548737966, "lat": 6.43427, "lon": -75.329627}, {"type": "node", "id": 4548737967, "lat": 6.434437, "lon": -75.329748}, {"type": "node", "id": 4548737968, "lat": 6.434559, "lon": -75.329861}, {"type": "node", "id": 4548737969, "lat": 6.4340346, "lon": -75.3288143}, {"type": "node", "id": 4548737973, "lat": 6.4339121, "lon": -75.3296446}, {"type": "node", "id": 4548737974, "lat": 6.4342137, "lon": -75.3290822}, {"type": "node", "id": 4548737975, "lat": 6.4339855, "lon": -75.3287121}, {"type": "node", "id": 4548737977, "lat": 6.4335065, "lon": -75.3295066}, {"type": "node", "id": 4548737978, "lat": 6.4355881, "lon": -75.3278013}, {"type": "node", "id": 4548737979, "lat": 6.435701, "lon": -75.3274819}, {"type": "node", "id": 4548737980, "lat": 6.4355781, "lon": -75.3268984}, {"type": "node", "id": 4548737981, "lat": 6.4354821, "lon": -75.3267723}, {"type": "node", "id": 4548737982, "lat": 6.4353589, "lon": -75.3266617}, {"type": "node", "id": 4548737983, "lat": 6.4351326, "lon": -75.326475}, {"type": "node", "id": 4548737984, "lat": 6.4348667, "lon": -75.3263381}, {"type": "node", "id": 4548737985, "lat": 6.434699, "lon": -75.3261805}, {"type": "node", "id": 4548737986, "lat": 6.434554, "lon": -75.3260515}, {"type": "node", "id": 4548737987, "lat": 6.434414, "lon": -75.3260035}, {"type": "node", "id": 4548737988, "lat": 6.4334407, "lon": -75.32599}, {"type": "node", "id": 4548737989, "lat": 6.4332544, "lon": -75.3259747}, {"type": "node", "id": 4548737990, "lat": 6.433081, "lon": -75.3259265}, {"type": "node", "id": 4548737991, "lat": 6.432675, "lon": -75.3256815}, {"type": "node", "id": 4548737992, "lat": 6.4323587, "lon": -75.3253822}, {"type": "node", "id": 4548737993, "lat": 6.4322293, "lon": -75.32514}, {"type": "node", "id": 4548737994, "lat": 6.4320878, "lon": -75.325022}, {"type": "node", "id": 4548737995, "lat": 6.4319596, "lon": -75.3249645}, {"type": "node", "id": 4548737996, "lat": 6.4316822, "lon": -75.324946}, {"type": "node", "id": 4548737997, "lat": 6.4315706, "lon": -75.3248878}, {"type": "node", "id": 4548737998, "lat": 6.431006, "lon": -75.324231}, {"type": "node", "id": 4548737999, "lat": 6.430951, "lon": -75.324162}, {"type": "node", "id": 4548738000, "lat": 6.4307963, "lon": -75.3240456}, {"type": "node", "id": 4548738001, "lat": 6.4303987, "lon": -75.3235261}, {"type": "node", "id": 4548738054, "lat": 6.4369086, "lon": -75.3275534}, {"type": "node", "id": 4548738055, "lat": 6.436929, "lon": -75.3275089}, {"type": "node", "id": 4548738056, "lat": 6.436979, "lon": -75.3273219}, {"type": "node", "id": 4548738057, "lat": 6.4370271, "lon": -75.3272151}, {"type": "node", "id": 4548738058, "lat": 6.4371302, "lon": -75.3271183}, {"type": "node", "id": 4548738059, "lat": 6.4375888, "lon": -75.3269269}, {"type": "node", "id": 4548738060, "lat": 6.4377269, "lon": -75.3269219}, {"type": "node", "id": 4548738061, "lat": 6.4378751, "lon": -75.327046}, {"type": "node", "id": 4548738062, "lat": 6.4379458, "lon": -75.3270585}, {"type": "node", "id": 4548738063, "lat": 6.4380281, "lon": -75.3270477}, {"type": "node", "id": 4548738064, "lat": 6.4383524, "lon": -75.3267652}, {"type": "node", "id": 4548738065, "lat": 6.4384565, "lon": -75.3267272}, {"type": "node", "id": 4548738066, "lat": 6.4385443, "lon": -75.3267494}, {"type": "node", "id": 4548738067, "lat": 6.4386177, "lon": -75.3268317}, {"type": "node", "id": 4548738068, "lat": 6.4386259, "lon": -75.3269446}, {"type": "node", "id": 4548738069, "lat": 6.4385871, "lon": -75.3270163}, {"type": "node", "id": 4548738070, "lat": 6.4384351, "lon": -75.3270711}, {"type": "node", "id": 4548738071, "lat": 6.4380883, "lon": -75.3272868}, {"type": "node", "id": 4548738072, "lat": 6.4379151, "lon": -75.3273429}, {"type": "node", "id": 4548738073, "lat": 6.4377751, "lon": -75.3273128}, {"type": "node", "id": 4548738074, "lat": 6.4376745, "lon": -75.3272374}, {"type": "node", "id": 4548738075, "lat": 6.437575, "lon": -75.3272049}, {"type": "node", "id": 4548738076, "lat": 6.437493, "lon": -75.3272009}, {"type": "node", "id": 4548738077, "lat": 6.437425, "lon": -75.3272379}, {"type": "node", "id": 4548738078, "lat": 6.437379, "lon": -75.3273419}, {"type": "node", "id": 4548738079, "lat": 6.437378, "lon": -75.3274729}, {"type": "node", "id": 4548738080, "lat": 6.437421, "lon": -75.3275939}, {"type": "node", "id": 4548738082, "lat": 6.437616, "lon": -75.3277169}, {"type": "node", "id": 4548738083, "lat": 6.437808, "lon": -75.3277189}, {"type": "node", "id": 4548738084, "lat": 6.438112, "lon": -75.3277729}, {"type": "node", "id": 4548738085, "lat": 6.43838, "lon": -75.3278729}, {"type": "node", "id": 4548738086, "lat": 6.438713, "lon": -75.3279559}, {"type": "node", "id": 4548738087, "lat": 6.438816, "lon": -75.327959}, {"type": "node", "id": 4548738088, "lat": 6.438969, "lon": -75.327929}, {"type": "node", "id": 4548738089, "lat": 6.439063, "lon": -75.327991}, {"type": "node", "id": 4548738090, "lat": 6.439368, "lon": -75.328614}, {"type": "node", "id": 4548738091, "lat": 6.439375, "lon": -75.328676}, {"type": "node", "id": 4548738093, "lat": 6.439362, "lon": -75.3287417}, {"type": "node", "id": 4548738094, "lat": 6.437034, "lon": -75.318962}, {"type": "node", "id": 4548738095, "lat": 6.436985, "lon": -75.318769}, {"type": "node", "id": 4548738096, "lat": 6.436926, "lon": -75.318659}, {"type": "node", "id": 4548738097, "lat": 6.436838, "lon": -75.318601}, {"type": "node", "id": 4548738098, "lat": 6.436753, "lon": -75.3186}, {"type": "node", "id": 4548738099, "lat": 6.436681, "lon": -75.318701}, {"type": "node", "id": 4548738100, "lat": 6.43664, "lon": -75.318892}, {"type": "node", "id": 4548738101, "lat": 6.43663, "lon": -75.319086}, {"type": "node", "id": 4548738102, "lat": 6.43666, "lon": -75.319317}, {"type": "node", "id": 4548738103, "lat": 6.4368426, "lon": -75.3195336}, {"type": "node", "id": 4548738104, "lat": 6.4369645, "lon": -75.3196755}, {"type": "node", "id": 4548738105, "lat": 6.4369726, "lon": -75.3198348}, {"type": "node", "id": 4548738106, "lat": 6.4368856, "lon": -75.3198725}, {"type": "node", "id": 4548738107, "lat": 6.4365268, "lon": -75.3196159}, {"type": "node", "id": 4548738108, "lat": 6.4363737, "lon": -75.3195546}, {"type": "node", "id": 4548738109, "lat": 6.4363092, "lon": -75.319621}, {"type": "node", "id": 4548738110, "lat": 6.436282, "lon": -75.319913}, {"type": "node", "id": 4548738111, "lat": 6.4362941, "lon": -75.3200146}, {"type": "node", "id": 4548738112, "lat": 6.436222, "lon": -75.3200788}, {"type": "node", "id": 4548738113, "lat": 6.436105, "lon": -75.3200608}, {"type": "node", "id": 4548738114, "lat": 6.4360005, "lon": -75.3200505}, {"type": "node", "id": 4548738115, "lat": 6.435965, "lon": -75.320149}, {"type": "node", "id": 4548738116, "lat": 6.4360077, "lon": -75.3202415}, {"type": "node", "id": 4548738117, "lat": 6.4360811, "lon": -75.3204465}, {"type": "node", "id": 4548738118, "lat": 6.4361771, "lon": -75.320777}, {"type": "node", "id": 4548738119, "lat": 6.436205, "lon": -75.321057}, {"type": "node", "id": 4548738120, "lat": 6.436169, "lon": -75.321191}, {"type": "node", "id": 4548738121, "lat": 6.436096, "lon": -75.321422}, {"type": "node", "id": 4548738122, "lat": 6.436111, "lon": -75.321588}, {"type": "node", "id": 4548738123, "lat": 6.4362421, "lon": -75.3216858}, {"type": "node", "id": 4548738124, "lat": 6.4363914, "lon": -75.3217677}, {"type": "node", "id": 4548738125, "lat": 6.436634, "lon": -75.321878}, {"type": "node", "id": 4548738126, "lat": 6.436838, "lon": -75.322011}, {"type": "node", "id": 4548738127, "lat": 6.437302, "lon": -75.322516}, {"type": "node", "id": 4548738128, "lat": 6.437359, "lon": -75.322662}, {"type": "node", "id": 4548738129, "lat": 6.4373083, "lon": -75.3228723}, {"type": "node", "id": 4548738130, "lat": 6.437186, "lon": -75.322988}, {"type": "node", "id": 4548738131, "lat": 6.436998, "lon": -75.323122}, {"type": "node", "id": 4548738132, "lat": 6.436849, "lon": -75.323169}, {"type": "node", "id": 4548738133, "lat": 6.436504, "lon": -75.323126}, {"type": "node", "id": 4548738134, "lat": 6.43628, "lon": -75.323189}, {"type": "node", "id": 4548738135, "lat": 6.436144, "lon": -75.323335}, {"type": "node", "id": 4548738136, "lat": 6.436104, "lon": -75.323515}, {"type": "node", "id": 4548738137, "lat": 6.4361617, "lon": -75.323657}, {"type": "node", "id": 4548738138, "lat": 6.4362927, "lon": -75.32383}, {"type": "node", "id": 4548738139, "lat": 6.436421, "lon": -75.3239654}, {"type": "node", "id": 4548738140, "lat": 6.436505, "lon": -75.3240514}, {"type": "node", "id": 4548738141, "lat": 6.4365883, "lon": -75.3241559}, {"type": "node", "id": 4548738142, "lat": 6.4367287, "lon": -75.3244609}, {"type": "node", "id": 4548738143, "lat": 6.436731, "lon": -75.324597}, {"type": "node", "id": 4548738144, "lat": 6.436725, "lon": -75.324858}, {"type": "node", "id": 4548738145, "lat": 6.436759, "lon": -75.324963}, {"type": "node", "id": 4548738146, "lat": 6.436749, "lon": -75.325116}, {"type": "node", "id": 4548738147, "lat": 6.436643, "lon": -75.325403}, {"type": "node", "id": 4548738148, "lat": 6.436664, "lon": -75.325545}, {"type": "node", "id": 4548738149, "lat": 6.436703, "lon": -75.325645}, {"type": "node", "id": 4548738150, "lat": 6.436748, "lon": -75.325899}, {"type": "node", "id": 4548738151, "lat": 6.436733, "lon": -75.326051}, {"type": "node", "id": 4548738152, "lat": 6.436652, "lon": -75.326171}, {"type": "node", "id": 4548738153, "lat": 6.436588, "lon": -75.326249}, {"type": "node", "id": 4548738154, "lat": 6.436583, "lon": -75.326316}, {"type": "node", "id": 4548738155, "lat": 6.4366463, "lon": -75.3264793}, {"type": "node", "id": 4548738156, "lat": 6.4366903, "lon": -75.3267036}, {"type": "node", "id": 4548738157, "lat": 6.436647, "lon": -75.3268685}, {"type": "node", "id": 4548738158, "lat": 6.436551, "lon": -75.3270421}, {"type": "node", "id": 4548738159, "lat": 6.4364604, "lon": -75.3272326}, {"type": "node", "id": 4548738160, "lat": 6.436462, "lon": -75.3273855}, {"type": "node", "id": 4548738161, "lat": 6.436518, "lon": -75.3275135}, {"type": "node", "id": 4548738162, "lat": 6.4365973, "lon": -75.3275951}, {"type": "node", "id": 4548738163, "lat": 6.4366683, "lon": -75.3276285}, {"type": "node", "id": 4548738164, "lat": 6.436746, "lon": -75.3276633}, {"type": "node", "id": 4548738165, "lat": 6.4369731, "lon": -75.3277607}, {"type": "node", "id": 4548738166, "lat": 6.4370247, "lon": -75.3278535}, {"type": "node", "id": 4548738167, "lat": 6.4370112, "lon": -75.3279447}, {"type": "node", "id": 4548738168, "lat": 6.4369689, "lon": -75.3279977}, {"type": "node", "id": 4548738169, "lat": 6.4369153, "lon": -75.3280254}, {"type": "node", "id": 4548738170, "lat": 6.4368375, "lon": -75.3280268}, {"type": "node", "id": 4548738171, "lat": 6.4366547, "lon": -75.3279087}, {"type": "node", "id": 4548738172, "lat": 6.436572, "lon": -75.327881}, {"type": "node", "id": 4548738173, "lat": 6.434858, "lon": -75.32966}, {"type": "node", "id": 4548738174, "lat": 6.436842, "lon": -75.328521}, {"type": "node", "id": 4548738175, "lat": 6.4352665, "lon": -75.3301266}, {"type": "node", "id": 4548738176, "lat": 6.434805, "lon": -75.330597}, {"type": "node", "id": 4548738178, "lat": 6.434775, "lon": -75.3322358}, {"type": "node", "id": 4548738179, "lat": 6.434716, "lon": -75.3323402}, {"type": "node", "id": 4548738180, "lat": 6.434767, "lon": -75.332636}, {"type": "node", "id": 4548738181, "lat": 6.434999, "lon": -75.331634}, {"type": "node", "id": 4548738182, "lat": 6.434966, "lon": -75.331569}, {"type": "node", "id": 4548738183, "lat": 6.435125, "lon": -75.331232}, {"type": "node", "id": 4548738184, "lat": 6.435128, "lon": -75.331153}, {"type": "node", "id": 4548738185, "lat": 6.435095, "lon": -75.33111}, {"type": "node", "id": 4548738186, "lat": 6.434942, "lon": -75.331034}, {"type": "node", "id": 4548738187, "lat": 6.4349037, "lon": -75.330979}, {"type": "node", "id": 4548738226, "lat": 6.434893, "lon": -75.331747}, {"type": "node", "id": 4548738227, "lat": 6.4367732, "lon": -75.3297774}, {"type": "node", "id": 4548738228, "lat": 6.4382871, "lon": -75.3294537}, {"type": "node", "id": 4548738229, "lat": 6.4386787, "lon": -75.3297201}, {"type": "node", "id": 4548738230, "lat": 6.438824, "lon": -75.3297874}, {"type": "node", "id": 4548738231, "lat": 6.4391017, "lon": -75.3297535}, {"type": "node", "id": 4548738232, "lat": 6.4392047, "lon": -75.3296936}, {"type": "node", "id": 4548738233, "lat": 6.439281, "lon": -75.329587}, {"type": "node", "id": 4548738234, "lat": 6.43928, "lon": -75.3293594}, {"type": "node", "id": 4548738235, "lat": 6.4392493, "lon": -75.3291637}, {"type": "node", "id": 4548738236, "lat": 6.439246, "lon": -75.3289921}, {"type": "node", "id": 4548738237, "lat": 6.439257, "lon": -75.3288563}, {"type": "node", "id": 4548738238, "lat": 6.439512, "lon": -75.3287852}, {"type": "node", "id": 4548738239, "lat": 6.4396263, "lon": -75.3289098}, {"type": "node", "id": 4548738240, "lat": 6.4397747, "lon": -75.3290528}, {"type": "node", "id": 4548738241, "lat": 6.4401537, "lon": -75.3292408}, {"type": "node", "id": 4548738242, "lat": 6.440321, "lon": -75.3291582}, {"type": "node", "id": 4548738243, "lat": 6.4404137, "lon": -75.3290686}, {"type": "node", "id": 4548738244, "lat": 6.4407061, "lon": -75.3283892}, {"type": "node", "id": 4548738245, "lat": 6.4407873, "lon": -75.3282885}, {"type": "node", "id": 4548738246, "lat": 6.4408606, "lon": -75.3282282}, {"type": "node", "id": 4548738247, "lat": 6.4410872, "lon": -75.3281222}, {"type": "node", "id": 4548738248, "lat": 6.4412218, "lon": -75.3281276}, {"type": "node", "id": 4548738249, "lat": 6.441491, "lon": -75.3282523}, {"type": "node", "id": 4548738250, "lat": 6.4419547, "lon": -75.3283811}, {"type": "node", "id": 4548738251, "lat": 6.4421547, "lon": -75.3282737}, {"type": "node", "id": 4548738252, "lat": 6.4421633, "lon": -75.3281827}, {"type": "node", "id": 4548738253, "lat": 6.4421577, "lon": -75.328098}, {"type": "node", "id": 4548738254, "lat": 6.4421263, "lon": -75.3280344}, {"type": "node", "id": 4548738255, "lat": 6.442085, "lon": -75.3279686}, {"type": "node", "id": 4548738256, "lat": 6.4419083, "lon": -75.3277049}, {"type": "node", "id": 4548738257, "lat": 6.4372631, "lon": -75.3331046}, {"type": "node", "id": 4548738258, "lat": 6.439032, "lon": -75.330043}, {"type": "node", "id": 4548738260, "lat": 6.440696, "lon": -75.331967}, {"type": "node", "id": 4548738261, "lat": 6.4406214, "lon": -75.3318287}, {"type": "node", "id": 4548738262, "lat": 6.4404583, "lon": -75.3316575}, {"type": "node", "id": 4548738264, "lat": 6.4414398, "lon": -75.3316541}, {"type": "node", "id": 4548738265, "lat": 6.441077, "lon": -75.331563}, {"type": "node", "id": 4548738273, "lat": 6.4401523, "lon": -75.3327819}, {"type": "node", "id": 4548738274, "lat": 6.4402366, "lon": -75.3326495}, {"type": "node", "id": 4548738275, "lat": 6.4396236, "lon": -75.3328681}, {"type": "node", "id": 4548738276, "lat": 6.4399796, "lon": -75.331155}, {"type": "node", "id": 4548738280, "lat": 6.4363759, "lon": -75.3339767}, {"type": "node", "id": 4548738281, "lat": 6.43564, "lon": -75.332248}, {"type": "node", "id": 4548738282, "lat": 6.435572, "lon": -75.332385}, {"type": "node", "id": 4548738283, "lat": 6.435453, "lon": -75.333273}, {"type": "node", "id": 4548738284, "lat": 6.435316, "lon": -75.333786}, {"type": "node", "id": 4548738285, "lat": 6.435316, "lon": -75.33392}, {"type": "node", "id": 4548738286, "lat": 6.435346, "lon": -75.334033}, {"type": "node", "id": 4548738287, "lat": 6.435435, "lon": -75.334143}, {"type": "node", "id": 4548738288, "lat": 6.435162, "lon": -75.335603}, {"type": "node", "id": 4548738289, "lat": 6.435443, "lon": -75.335253}, {"type": "node", "id": 4548738290, "lat": 6.43553, "lon": -75.335196}, {"type": "node", "id": 4548738291, "lat": 6.435626, "lon": -75.335175}, {"type": "node", "id": 4548738296, "lat": 6.4357724, "lon": -75.3354729}, {"type": "node", "id": 4548738297, "lat": 6.4357345, "lon": -75.3355764}, {"type": "node", "id": 4548738298, "lat": 6.4356827, "lon": -75.3356732}, {"type": "node", "id": 4548738299, "lat": 6.4356193, "lon": -75.33576}, {"type": "node", "id": 4548738300, "lat": 6.4344063, "lon": -75.3367512}, {"type": "node", "id": 4548738304, "lat": 6.442507, "lon": -75.328973}, {"type": "node", "id": 4548738307, "lat": 6.4415623, "lon": -75.3286067}, {"type": "node", "id": 4548738308, "lat": 6.4413473, "lon": -75.3286569}, {"type": "node", "id": 4548738309, "lat": 6.441248, "lon": -75.3287042}, {"type": "node", "id": 4548738312, "lat": 6.4356173, "lon": -75.3340628}, {"type": "node", "id": 4548738313, "lat": 6.4355338, "lon": -75.334301}, {"type": "node", "id": 4548738316, "lat": 6.4358153, "lon": -75.3354347}, {"type": "node", "id": 4548738317, "lat": 6.435918, "lon": -75.334455}, {"type": "node", "id": 4548738318, "lat": 6.435865, "lon": -75.334083}, {"type": "node", "id": 4548738319, "lat": 6.435824, "lon": -75.333987}, {"type": "node", "id": 4548738322, "lat": 6.436081, "lon": -75.334659}, {"type": "node", "id": 4548738327, "lat": 6.434968, "lon": -75.336938}, {"type": "node", "id": 4548738330, "lat": 6.4354763, "lon": -75.3371028}, {"type": "node", "id": 4548738335, "lat": 6.434955, "lon": -75.336968}, {"type": "node", "id": 4911050877, "lat": 6.4370197, "lon": -75.3308774}, {"type": "node", "id": 4911050878, "lat": 6.4369641, "lon": -75.3309381}, {"type": "node", "id": 4911050879, "lat": 6.4365547, "lon": -75.3313941}, {"type": "node", "id": 4930511780, "lat": 6.4459717, "lon": -75.3315706}, {"type": "node", "id": 4930511876, "lat": 6.4414572, "lon": -75.3323272}, {"type": "node", "id": 4930511877, "lat": 6.4416945, "lon": -75.3324173}, {"type": "node", "id": 4930511878, "lat": 6.4415507, "lon": -75.3325701}, {"type": "node", "id": 4930511879, "lat": 6.4414203, "lon": -75.3323881}, {"type": "node", "id": 5629656522, "lat": 6.4411494, "lon": -75.3310736}, {"type": "node", "id": 5629656523, "lat": 6.441224, "lon": -75.3311964}, {"type": "node", "id": 5629656541, "lat": 6.4400721, "lon": -75.3328218}, {"type": "node", "id": 5629656545, "lat": 6.4402113, "lon": -75.3327143}, {"type": "node", "id": 5629656548, "lat": 6.4393634, "lon": -75.3331319}, {"type": "node", "id": 5629656550, "lat": 6.4398802, "lon": -75.3327881}, {"type": "node", "id": 5629656551, "lat": 6.4392871, "lon": -75.3305327}, {"type": "node", "id": 5629656552, "lat": 6.4399449, "lon": -75.3312042}, {"type": "node", "id": 5629656554, "lat": 6.4388663, "lon": -75.33021}, {"type": "node", "id": 5629656606, "lat": 6.4304095, "lon": -75.3276477}, {"type": "node", "id": 5629656607, "lat": 6.4299985, "lon": -75.3275951}, {"type": "node", "id": 5629656608, "lat": 6.4322344, "lon": -75.3266121}, {"type": "node", "id": 5638367177, "lat": 6.4374915, "lon": -75.3276697}, {"type": "node", "id": 5676291253, "lat": 6.4366383, "lon": -75.3191788}, {"type": "node", "id": 5676291432, "lat": 6.4361582, "lon": -75.321636}, {"type": "node", "id": 5676291449, "lat": 6.4371301, "lon": -75.3230278}, {"type": "node", "id": 5676291485, "lat": 6.4390357, "lon": -75.327885}, {"type": "node", "id": 5676291486, "lat": 6.4390235, "lon": -75.3278328}, {"type": "node", "id": 5676291487, "lat": 6.4390357, "lon": -75.3277652}, {"type": "node", "id": 5676291488, "lat": 6.4390937, "lon": -75.3276915}, {"type": "node", "id": 5676291489, "lat": 6.4391486, "lon": -75.3276424}, {"type": "node", "id": 5676291490, "lat": 6.4392554, "lon": -75.3275502}, {"type": "node", "id": 5676291491, "lat": 6.4393714, "lon": -75.3274735}, {"type": "node", "id": 5676291492, "lat": 6.4395301, "lon": -75.3273414}, {"type": "node", "id": 5676291493, "lat": 6.4396247, "lon": -75.3272523}, {"type": "node", "id": 5676291494, "lat": 6.4397132, "lon": -75.3271203}, {"type": "node", "id": 5676291495, "lat": 6.4398658, "lon": -75.3269452}, {"type": "node", "id": 5676291496, "lat": 6.4400158, "lon": -75.3267975}, {"type": "node", "id": 5676291497, "lat": 6.440141, "lon": -75.3267028}, {"type": "node", "id": 5676291498, "lat": 6.4402319, "lon": -75.3265777}, {"type": "node", "id": 5676291499, "lat": 6.4402624, "lon": -75.3264452}, {"type": "node", "id": 5676291500, "lat": 6.440235, "lon": -75.3262919}, {"type": "node", "id": 5676291501, "lat": 6.4401618, "lon": -75.3261651}, {"type": "node", "id": 5676291502, "lat": 6.4400916, "lon": -75.3260362}, {"type": "node", "id": 5676291503, "lat": 6.440058, "lon": -75.3259256}, {"type": "node", "id": 5676291504, "lat": 6.4400824, "lon": -75.3256891}, {"type": "node", "id": 5676291505, "lat": 6.4401313, "lon": -75.3255448}, {"type": "node", "id": 5676291506, "lat": 6.4402106, "lon": -75.3253851}, {"type": "node", "id": 5676291507, "lat": 6.440354, "lon": -75.3252039}, {"type": "node", "id": 5676291508, "lat": 6.4404517, "lon": -75.3249459}, {"type": "node", "id": 5676291509, "lat": 6.4404761, "lon": -75.3247585}, {"type": "node", "id": 5676291510, "lat": 6.4404944, "lon": -75.3245835}, {"type": "node", "id": 5676291511, "lat": 6.4405158, "lon": -75.3243501}, {"type": "node", "id": 5676291512, "lat": 6.4405158, "lon": -75.3241044}, {"type": "node", "id": 5676291513, "lat": 6.4405066, "lon": -75.3239754}, {"type": "node", "id": 5676368220, "lat": 6.4248674, "lon": -75.3269835}, {"type": "node", "id": 5732848327, "lat": 6.4274922, "lon": -75.3285555}, {"type": "node", "id": 5732848367, "lat": 6.4298888, "lon": -75.3277538}, {"type": "node", "id": 6128206788, "lat": 6.4420866, "lon": -75.3283502}, {"type": "node", "id": 6128206789, "lat": 6.4354213, "lon": -75.3267123}, {"type": "node", "id": 6128206790, "lat": 6.4381659, "lon": -75.329577}, {"type": "node", "id": 6128206791, "lat": 6.4380214, "lon": -75.3297241}, {"type": "node", "id": 6128206792, "lat": 6.4387497, "lon": -75.3297678}, {"type": "node", "id": 6128206793, "lat": 6.4389203, "lon": -75.3297879}, {"type": "node", "id": 6128206794, "lat": 6.4392535, "lon": -75.3296497}, {"type": "node", "id": 6128206795, "lat": 6.4392948, "lon": -75.3294902}, {"type": "node", "id": 6128206796, "lat": 6.4393094, "lon": -75.3287901}, {"type": "node", "id": 6128206799, "lat": 6.435606, "lon": -75.3323051}, {"type": "node", "id": 6128206800, "lat": 6.4414523, "lon": -75.3286225}, {"type": "node", "id": 6128206801, "lat": 6.4425924, "lon": -75.3276059}, {"type": "node", "id": 6128206802, "lat": 6.4425171, "lon": -75.3278305}, {"type": "node", "id": 6128206803, "lat": 6.442599, "lon": -75.3275207}, {"type": "node", "id": 6128206829, "lat": 6.4430861, "lon": -75.3271593}, {"type": "node", "id": 6128206830, "lat": 6.4424638, "lon": -75.3319417}, {"type": "node", "id": 6128206831, "lat": 6.4446973, "lon": -75.3317191}, {"type": "node", "id": 6128206832, "lat": 6.4433187, "lon": -75.331821}, {"type": "node", "id": 8506611275, "lat": 6.4415266, "lon": -75.3321833}, {"type": "node", "id": 8506611276, "lat": 6.4416069, "lon": -75.3322178}, {"type": "node", "id": 8506611277, "lat": 6.441633, "lon": -75.3323117}, {"type": "node", "id": 9314354863, "lat": 6.4343445, "lon": -75.3274909}, {"type": "node", "id": 9314354864, "lat": 6.4334035, "lon": -75.3277506}, {"type": "node", "id": 9314354865, "lat": 6.4329713, "lon": -75.3265336}, {"type": "node", "id": 9314354877, "lat": 6.4340669, "lon": -75.3288872}, {"type": "node", "id": 9314374460, "lat": 6.4349088, "lon": -75.3317305}, {"type": "node", "id": 9314374461, "lat": 6.4349737, "lon": -75.3316795}, {"type": "node", "id": 9314374462, "lat": 6.4327846, "lon": -75.3264559}, {"type": "node", "id": 9314374463, "lat": 6.4327617, "lon": -75.3265378}, {"type": "node", "id": 9469152730, "lat": 6.4333245, "lon": -75.3287271}, {"type": "node", "id": 9469152731, "lat": 6.4330446, "lon": -75.3287619}, {"type": "node", "id": 9469152732, "lat": 6.4326143, "lon": -75.3269198}, {"type": "node", "id": 9469152733, "lat": 6.4327274, "lon": -75.326623}, {"type": "node", "id": 9469152734, "lat": 6.4330425, "lon": -75.32631}, {"type": "node", "id": 9469152735, "lat": 6.4329375, "lon": -75.3262856}, {"type": "node", "id": 9469152736, "lat": 6.4332587, "lon": -75.3267917}, {"type": "node", "id": 9469152737, "lat": 6.4330459, "lon": -75.3279613}, {"type": "node", "id": 9469152738, "lat": 6.4329281, "lon": -75.3278693}, {"type": "node", "id": 9469152739, "lat": 6.4326854, "lon": -75.3273632}, {"type": "node", "id": 9469152740, "lat": 6.4338249, "lon": -75.3283594}, {"type": "node", "id": 9469152741, "lat": 6.433737, "lon": -75.3282603}, {"type": "node", "id": 9469152742, "lat": 6.4336842, "lon": -75.3281577}, {"type": "node", "id": 9469152743, "lat": 6.4337089, "lon": -75.3282196}, {"type": "node", "id": 9469152744, "lat": 6.4335717, "lon": -75.3279542}, {"type": "node", "id": 9469152745, "lat": 6.4340588, "lon": -75.3269568}, {"type": "node", "id": 9469152746, "lat": 6.434272, "lon": -75.3272465}, {"type": "node", "id": 9469152747, "lat": 6.4341134, "lon": -75.3270628}, {"type": "node", "id": 9469152748, "lat": 6.4346292, "lon": -75.3274624}, {"type": "node", "id": 9469152749, "lat": 6.4345692, "lon": -75.3274289}, {"type": "node", "id": 9469152750, "lat": 6.4341441, "lon": -75.3279345}, {"type": "node", "id": 9469152751, "lat": 6.4341521, "lon": -75.3280029}, {"type": "node", "id": 9471314290, "lat": 6.4380208, "lon": -75.3343704}, {"type": "node", "id": 9923902558, "lat": 6.4424465, "lon": -75.3279563}, {"type": "node", "id": 9923902559, "lat": 6.4424571, "lon": -75.3279566}, {"type": "node", "id": 9923902560, "lat": 6.4424371, "lon": -75.3279465}, {"type": "node", "id": 9924372708, "lat": 6.4335604, "lon": -75.3268448}, {"type": "node", "id": 9924427147, "lat": 6.4373527, "lon": -75.3269874}, {"type": "node", "id": 9924427151, "lat": 6.4392788, "lon": -75.3356136}, {"type": "node", "id": 9924427152, "lat": 6.4392015, "lon": -75.3356056}, {"type": "node", "id": 9924427153, "lat": 6.4373491, "lon": -75.3227592}, {"type": "node", "id": 9924427154, "lat": 6.4366881, "lon": -75.32658}, {"type": "node", "id": 9924499183, "lat": 6.434917, "lon": -75.3309466}, {"type": "node", "id": 9924499184, "lat": 6.4349157, "lon": -75.3310163}, {"type": "node", "id": 9924499185, "lat": 6.4347558, "lon": -75.3322837}, {"type": "node", "id": 9924499186, "lat": 6.4347198, "lon": -75.3324312}, {"type": "node", "id": 9924499187, "lat": 6.4336897, "lon": -75.3260207}, {"type": "node", "id": 9924499192, "lat": 6.4322037, "lon": -75.3298415}, {"type": "node", "id": 9924499193, "lat": 6.4321917, "lon": -75.329694}, {"type": "node", "id": 9924499194, "lat": 6.4321891, "lon": -75.3297544}, {"type": "node", "id": 9924499195, "lat": 6.4318732, "lon": -75.3293809}, {"type": "node", "id": 9924499196, "lat": 6.4318432, "lon": -75.3294194}, {"type": "node", "id": 9924499197, "lat": 6.4318985, "lon": -75.3293775}, {"type": "node", "id": 9924499198, "lat": 6.4318559, "lon": -75.3293949}, {"type": "node", "id": 9924499199, "lat": 6.4376499, "lon": -75.326922}, {"type": "node", "id": 9924499200, "lat": 6.4374686, "lon": -75.3269491}, {"type": "node", "id": 9924499210, "lat": 6.4390642, "lon": -75.3333539}, {"type": "node", "id": 9924499211, "lat": 6.4386764, "lon": -75.3335188}, {"type": "node", "id": 9924610813, "lat": 6.4354821, "lon": -75.3370862}, {"type": "node", "id": 9924610814, "lat": 6.4354781, "lon": -75.3370634}, {"type": "node", "id": 9924610815, "lat": 6.4354577, "lon": -75.3370453}, {"type": "node", "id": 9941608221, "lat": 6.4423992, "lon": -75.3278889}, {"type": "node", "id": 9941608222, "lat": 6.4389243, "lon": -75.3334129}, {"type": "node", "id": 10917227331, "lat": 6.4413317, "lon": -75.332543}, {"type": "node", "id": 11811908237, "lat": 6.4283643, "lon": -75.3296739}, {"type": "node", "id": 11811908241, "lat": 6.4381213, "lon": -75.3269962}, {"type": "node", "id": 11811908242, "lat": 6.432294, "lon": -75.3292397}, {"type": "node", "id": 11811908243, "lat": 6.432313, "lon": -75.3292632}, {"type": "node", "id": 11811908244, "lat": 6.432329, "lon": -75.3292649}, {"type": "node", "id": 11811908245, "lat": 6.4324769, "lon": -75.3279841}, {"type": "node", "id": 11811908246, "lat": 6.434236, "lon": -75.3259966}, {"type": "node", "id": 11811908247, "lat": 6.4338735, "lon": -75.3261039}, {"type": "node", "id": 11811908248, "lat": 6.4356623, "lon": -75.3276414}, {"type": "node", "id": 11811908249, "lat": 6.4356925, "lon": -75.327185}, {"type": "node", "id": 11811908250, "lat": 6.4358313, "lon": -75.3356627}, {"type": "node", "id": 11811908251, "lat": 6.4355735, "lon": -75.3341538}, {"type": "node", "id": 11811908252, "lat": 6.4355293, "lon": -75.3344761}, {"type": "node", "id": 11811908253, "lat": 6.4411483, "lon": -75.3310163}, {"type": "node", "id": 11811908254, "lat": 6.4411659, "lon": -75.3311255}, {"type": "node", "id": 11811908255, "lat": 6.4412807, "lon": -75.3312258}, {"type": "node", "id": 11811908256, "lat": 6.4418494, "lon": -75.3323212}, {"type": "node", "id": 12998447127, "lat": 6.436504, "lon": -75.3279566}, {"type": "node", "id": 12998451553, "lat": 6.43444, "lon": -75.3371018}, {"type": "way", "id": 208360738, "nodes": [8506611277, 3474224971], "tags": {"highway": "primary", "lanes": "2", "maxspeed": "80", "name": "Conexi\u00f3n a Barbosa", "oneway": "yes", "source": "gpx", "surface": "asphalt"}}, {"type": "way", "id": 315181703, "nodes": [1397149192, 8506611275, 336765604], "tags": {"autor": "S.D.", "highway": "primary", "oneway": "yes", "ref": "62", "source": "GPS"}}, {"type": "way", "id": 340209605, "nodes": [3474224955, 3474224954, 4930511879, 3474224956, 4930511876, 1397149192, 3474224959, 3474224961, 3474224963, 8506611277, 3474224966, 3474224967, 4930511877, 3474224968, 3474224969, 3474224965, 3474224964, 3474224962, 4930511878, 3474224960, 3474224958, 3474224957, 3474224955], "tags": {"highway": "primary", "junction": "roundabout", "ref": "62", "surface": "asphalt"}}, {"type": "way", "id": 340209607, "nodes": [336765604, 8506611276, 3474224963], "tags": {"autor": "S.D.", "highway": "primary", "oneway": "yes", "ref": "62", "source": "GPS"}}, {"type": "way", "id": 340209609, "nodes": [3474224971, 2186616862, 6128206830, 3474224972, 6128206832, 2186616865, 6128206831, 2186616868, 4930511780], "tags": {"highway": "primary", "lanes": "2", "maxspeed": "80", "name": "Conexi\u00f3n a Barbosa", "oneway": "no", "source": "gpx", "surface": "asphalt"}}, {"type": "way", "id": 340209610, "nodes": [3474224971, 11811908256, 3474224968], "tags": {"highway": "primary", "lanes": "2", "maxspeed": "80", "name": "Conexi\u00f3n a Barbosa", "oneway": "yes", "source": "gpx", "surface": "asphalt"}}, {"type": "way", "id": 340209615, "nodes": [3474224960, 10917227331, 3474224952], "tags": {"autor": "S.D.", "highway": "primary", "name": "Hatillo - Barbosa", "note": "V\u00eda vieja", "oneway": "yes", "ref": "62", "source": "GPS", "surface": "asphalt"}}, {"type": "way", "id": 340209616, "nodes": [3474224952, 1397149184, 3474224956], "tags": {"autor": "S.D.", "highway": "primary", "name": "Hatillo - Barbosa", "note": "V\u00eda vieja", "oneway": "yes", "ref": "62", "source": "GPS", "surface": "asphalt"}}, {"type": "way", "id": 424078938, "nodes": [4235522204, 4548737084, 4548737085, 4548737086, 4548737083, 4548737082], "tags": {"highway": "residential"}}, {"type": "way", "id": 458950951, "nodes": [4548737069, 4548737070], "tags": {"bridge": "yes", "highway": "tertiary", "layer": "1"}}, {"type": "way", "id": 458950952, "nodes": [4548737407, 4548737408, 4548737409, 11811908250, 4548737410, 4548738316, 4548737549, 4548737550, 4548737551, 4548737552, 11811908252, 4548738313, 4548737553, 11811908251, 4548738312, 4548737554, 4548737070], "tags": {"highway": "tertiary"}}, {"type": "way", "id": 458950953, "nodes": [4548738283, 4548737071], "tags": {"bridge": "yes", "highway": "residential", "layer": "1"}}, {"type": "way", "id": 458950954, "nodes": [4548737553, 4548738287, 4548738286, 4548738285, 4548738284, 4548737071], "tags": {"highway": "residential"}}, {"type": "way", "id": 458950955, "nodes": [4548737073, 4548737397, 4548737398, 4548737396, 336765606, 4548737403, 4548737404, 3782066940, 9924499211, 4235522208, 9941608222, 9924499210, 3782066942, 4548737088, 4548737079, 3474224952], "tags": {"autor": "S.D.", "highway": "primary", "lanes": "2", "name": "Hatillo - Barbosa", "note": "V\u00eda vieja", "oneway": "no", "ref": "62", "source": "GPS", "surface": "asphalt"}}, {"type": "way", "id": 458950956, "nodes": [4548737072, 4548737073], "tags": {"autor": "S.D.", "bridge": "yes", "highway": "primary", "lanes": "2", "layer": "1", "name": "Hatillo - Barbosa", "note": "V\u00eda vieja", "oneway": "no", "ref": "62", "source": "GPS", "surface": "asphalt"}}, {"type": "way", "id": 458950957, "nodes": [4548737826, 4548737825, 4548737824, 4548737592, 4548737593, 1397149007], "tags": {"highway": "residential"}}, {"type": "way", "id": 458950959, "nodes": [4548737451, 4548737079], "tags": {"highway": "residential", "oneway": "no"}}, {"type": "way", "id": 458950962, "nodes": [4548738280, 4548737391, 4548737389, 4548737392], "tags": {"highway": "residential"}}, {"type": "way", "id": 458950963, "nodes": [4548737543, 4548737544, 4548737555, 4548738280], "tags": {"highway": "residential"}}, {"type": "way", "id": 458950965, "nodes": [4548737782, 9924427151, 4548737491], "tags": {"highway": "residential"}}, {"type": "way", "id": 458950966, "nodes": [4548737777, 4548737491, 4548737778, 4548737779, 4548737780, 4548737490, 4548737395, 4548737403], "tags": {"highway": "tertiary", "oneway": "no", "surface": "asphalt"}}, {"type": "way", "id": 458950968, "nodes": [4548737403, 4548737492, 4548737558, 4548737539], "tags": {"highway": "tertiary", "oneway": "yes"}}, {"type": "way", "id": 458950969, "nodes": [4548737522, 4548738173, 4548737521], "tags": {"highway": "residential"}}, {"type": "way", "id": 458950970, "nodes": [4548738228, 6128206790, 6128206791, 4548737535, 4548737534, 4548737563], "tags": {"highway": "residential"}}, {"type": "way", "id": 458950972, "nodes": [4548737406, 4548737891, 4548737890, 5629656608, 4548737876], "tags": {"highway": "unclassified", "surface": "asphalt"}}, {"type": "way", "id": 458950973, "nodes": [4548737911, 4548737912, 5732848367, 4548737910, 5629656607, 4548737909, 5629656606, 4548737908, 4548737907, 4548737906, 11811908245, 4548737905], "tags": {"highway": "residential", "surface": "paved"}}, {"type": "way", "id": 458950975, "nodes": [4548737552, 4548738317], "tags": {"highway": "residential"}}, {"type": "way", "id": 458950977, "nodes": [4548737400, 9924610815, 9924610814, 9924610813, 4548738330], "tags": {"highway": "residential"}}, {"type": "way", "id": 458950990, "nodes": [4548737664, 4548737661, 4548737660, 4548737077], "tags": {"highway": "residential"}}, {"type": "way", "id": 458950991, "nodes": [4548737082, 11811908253, 5629656522, 11811908254, 4548737665, 5629656523, 11811908255, 4548737080, 4548737664, 4548737663, 4548737662, 4548737078], "tags": {"highway": "residential", "surface": "asphalt"}}, {"type": "way", "id": 458950992, "nodes": [4548737667, 4548737666, 8506611275], "tags": {"highway": "residential", "surface": "unpaved"}}, {"type": "way", "id": 458950993, "nodes": [4548737489, 4548737559, 4548737488], "tags": {"highway": "tertiary", "oneway": "yes"}}, {"type": "way", "id": 458951001, "nodes": [4548737484, 4548737483, 4235522208], "tags": {"highway": "residential"}}, {"type": "way", "id": 458951002, "nodes": [4548737490, 4548737493], "tags": {"highway": "residential"}}, {"type": "way", "id": 458951003, "nodes": [4548737398, 9471314290, 4548737493, 9924427152, 4548737782], "tags": {"highway": "residential"}}, {"type": "way", "id": 458951005, "nodes": [4548737787, 4548737786, 4548737581], "tags": {"highway": "residential"}}, {"type": "way", "id": 458951008, "nodes": [4548737804, 9941608221, 9923902560, 9923902558, 9923902559, 4548737822], "tags": {"highway": "residential"}}, {"type": "way", "id": 458951013, "nodes": [4548737822, 6128206802, 4548737821, 6128206801, 6128206803, 4548737592], "tags": {"highway": "residential"}}, {"type": "way", "id": 458951021, "nodes": [4548737582, 4548737857, 4548737856, 4548737580], "tags": {"highway": "residential"}}, {"type": "way", "id": 458951023, "nodes": [4548737412, 4548737405], "tags": {"highway": "residential"}}, {"type": "way", "id": 458951025, "nodes": [4548737513, 11811908247, 4548737869, 4548737868, 4548737516, 9469152745, 9469152747, 4548737867, 9469152746, 4548737866, 9314354863, 4548737517, 9469152750, 9469152751, 4548737865, 4548737521], "tags": {"highway": "residential"}}, {"type": "way", "id": 458951026, "nodes": [4548737871, 4548737870, 4548737514], "tags": {"highway": "residential", "surface": "asphalt"}}, {"type": "way", "id": 458951027, "nodes": [4548737872, 4548737512], "tags": {"highway": "residential"}}, {"type": "way", "id": 458951028, "nodes": [9314374462, 4548737512, 9469152735, 4548737874, 9469152734, 4548737514, 4548737873, 9924372708, 4548737516], "tags": {"highway": "residential", "surface": "asphalt"}}, {"type": "way", "id": 458951029, "nodes": [4548737511, 9314354864], "tags": {"highway": "residential", "surface": "asphalt"}}, {"type": "way", "id": 458951030, "nodes": [4548737876, 9469152732, 4548737889, 4548737511, 4548737888, 9469152739, 4548737887, 4548737886, 4548737885, 4548737884, 4548737883, 4548737882, 4548737881, 4548737880, 9469152738, 4548737879, 9469152737, 4548737905], "tags": {"highway": "residential", "surface": "asphalt"}}, {"type": "way", "id": 458951031, "nodes": [4548737526, 4548737525], "tags": {"highway": "residential"}}, {"type": "way", "id": 458951032, "nodes": [9314354877, 4548737898, 4548737974, 4548737897, 4548737896, 4548737522, 4548737895, 4548737527, 4548737894, 3782066930], "tags": {"highway": "residential", "surface": "asphalt"}}, {"type": "way", "id": 458951034, "nodes": [4548737919, 4548737918, 4548737917, 4548737925], "tags": {"highway": "residential"}}, {"type": "way", "id": 458951035, "nodes": [4548737929, 4548737928, 9924499196, 9924499198, 9924499195, 9924499197, 4548737927, 4548737926, 4548737925, 4548737924, 4548737923, 4548737922, 4548737921, 11811908242, 4548737920, 11811908243, 11811908244, 4548737933], "tags": {"highway": "residential"}}, {"type": "way", "id": 458951036, "nodes": [4548737937, 4548737936, 9924499192, 9924499194, 9924499193, 4548737935, 4548737934, 4548737933, 4548737932, 4548737931, 4548737930], "tags": {"highway": "residential"}}, {"type": "way", "id": 458951039, "nodes": [4548737964, 4548737963, 4548737962, 4548737961, 9469152730, 4548737960, 9469152731, 4548737959, 4548737930, 4548737958, 4548737957, 4548737956, 4548737955, 4548737954, 4548737953, 4548737952, 4548737951, 4548737950, 4548737949, 4548737948, 4548737947, 4548737510, 4548737946, 4548737945, 4548737944, 4548737943, 4548737942], "tags": {"highway": "residential", "surface": "concrete"}}, {"type": "way", "id": 458951040, "nodes": [4548737968, 4548737967, 4548737966, 4548737965], "tags": {"highway": "residential"}}, {"type": "way", "id": 458951042, "nodes": [4548737977, 4548737964, 4548737975], "tags": {"highway": "residential"}}, {"type": "way", "id": 458951043, "nodes": [4548737518, 4548737978], "tags": {"highway": "residential"}}, {"type": "way", "id": 458951045, "nodes": [5638367177, 4548738080, 4548738079, 4548738078, 4548738077, 4548738076, 4548738075, 4548738074, 4548738073, 4548738072, 4548738071, 4548738070, 4548738069, 4548738068, 4548738067, 4548738066, 4548738065, 4548738064, 11811908241, 4548738063, 4548738062, 4548738061, 4548738060, 9924499199, 4548738059, 9924499200, 9924427147, 4548738058, 4548738057, 4548738056, 4548738055, 4548738054, 4548737578], "tags": {"highway": "unclassified", "surface": "unpaved"}}, {"type": "way", "id": 458951048, "nodes": [4548738172, 4548738171, 4548738170, 4548738169, 4548738168, 4548738167, 4548738166, 4548738165, 4548737578, 4548738164, 4548738163, 4548738162, 4548738161, 4548738160, 4548738159, 4548738158, 4548738157, 4548738156, 9924427154, 4548738155, 4548738154, 4548738153, 4548738152, 4548738151, 4548738150, 4548738149, 4548738148, 4548738147, 4548738146, 4548738145, 4548738144, 4548738143, 4548738142, 4548738141, 4548738140, 4548738139, 4548738138, 4548738137, 4548738136, 4548738135, 4548738134, 4548738133, 4548738132, 4548738131, 5676291449, 4548738130, 4548738129, 9924427153, 4548738128, 4548738127, 4548738126, 4548738125, 4548738124, 4548738123, 5676291432, 4548738122, 4548738121, 4548738120, 4548738119, 4548738118, 4548738117, 4548738116, 4548738115, 4548738114, 4548738113, 4548738112, 4548738111, 4548738110, 4548738109, 4548738108, 4548738107, 4548738106, 4548738105, 4548738104, 4548738103, 4548738102, 5676291253, 4548738101, 4548738100, 4548738099, 4548738098, 4548738097, 4548738096, 4548738095, 4548738094, 4074260166], "tags": {"highway": "unclassified", "surface": "dirt"}}, {"type": "way", "id": 458951050, "nodes": [4548738176, 4548737526, 4548738175, 4548737527, 4548737528], "tags": {"highway": "residential"}}, {"type": "way", "id": 458951051, "nodes": [4548738180, 9924499186, 4548738179, 9924499185, 4548738178, 4548737523], "tags": {"highway": "residential"}}, {"type": "way", "id": 458951052, "nodes": [4548737525, 9924499183, 4548738187, 9924499184, 4548738186, 4548738185, 4548738184, 4548738183, 4548738182, 4548738181, 4548737524], "tags": {"highway": "residential"}}, {"type": "way", "id": 458951053, "nodes": [4548737531, 4548737532, 4548738227, 4548737533, 4548737412, 4548737894, 4548737524, 9314374461], "tags": {"highway": "residential"}}, {"type": "way", "id": 458951054, "nodes": [4548738256, 4548738255, 4548738254, 4548738253, 4548738252, 4548738251, 6128206788, 4548738250, 4548737590, 4548738249, 4548738248, 4548738247, 4548737589, 4548738246, 4548738245, 4548738244, 4548737588, 4548737587, 4548738243, 4548738242, 4548738241, 4548737582, 4548738240, 4548738239, 4548738238, 4548738093, 6128206796, 4548738237, 4548738236, 4548738235, 4548738234, 6128206795, 4548738233, 6128206794, 4548738232, 4548738231, 4548737564, 6128206793, 4548738230, 6128206792, 4548738229, 4548738228], "tags": {"highway": "residential"}}, {"type": "way", "id": 458951055, "nodes": [4548737411, 4548737540, 4548737557, 4548738257, 4548737495, 4548737494, 4548737396], "tags": {"highway": "residential"}}, {"type": "way", "id": 458951056, "nodes": [4548737556, 4548737541], "tags": {"highway": "residential"}}, {"type": "way", "id": 458951057, "nodes": [4548737542, 4548737544, 4548737541, 4548737540, 4548737539], "tags": {"highway": "residential", "lanes": "2", "surface": "paved"}}, {"type": "way", "id": 458951058, "nodes": [4548737451, 4548737459, 4548737458, 4548737457, 4548737456, 4548737455, 4548737454, 4548737453], "tags": {"highway": "residential", "oneway": "yes", "surface": "asphalt"}}, {"type": "way", "id": 458951059, "nodes": [4548737594, 4548737450, 4548738276, 4548737449, 4548737448, 4548738262, 4548738261, 4548737447, 4548738260, 4548737451], "tags": {"highway": "residential", "oneway": "yes", "surface": "asphalt"}}, {"type": "way", "id": 458951060, "nodes": [4548737446, 4548737667, 4548738264], "tags": {"highway": "residential", "surface": "unpaved"}}, {"type": "way", "id": 458951061, "nodes": [4548738265, 4548737446, 4548737447], "tags": {"highway": "residential", "surface": "unpaved"}}, {"type": "way", "id": 458951070, "nodes": [4548737476, 4548738275], "tags": {"highway": "residential", "surface": "paved"}}, {"type": "way", "id": 458951075, "nodes": [4548737486, 4548737483], "tags": {"highway": "residential"}}, {"type": "way", "id": 458951076, "nodes": [4548737487, 4548737484, 4548737481, 4548737474, 4548737461, 4548737453], "tags": {"highway": "residential", "surface": "asphalt"}}, {"type": "way", "id": 458951084, "nodes": [4548738280, 4548737503, 4548737500, 4548738257, 4548737492, 4548737488], "tags": {"highway": "residential"}}, {"type": "way", "id": 458951085, "nodes": [4548738283, 4548737542, 4548737543, 4548738282, 6128206799, 4548738281, 4548737411, 3782066930], "tags": {"highway": "residential"}}, {"type": "way", "id": 458951086, "nodes": [4548737550, 4548738291, 4548738290, 4548738289, 4548737504, 4548738288], "tags": {"highway": "residential"}}, {"type": "way", "id": 458951092, "nodes": [4548738300, 4548737505, 4548737506, 4548737507, 4548737508, 4548737509, 4548738299, 4548738298, 4548738297, 4548738296, 4548737549], "tags": {"highway": "residential"}}, {"type": "way", "id": 458951094, "nodes": [4548737559, 4548737560, 4548737561, 4548737562, 4548737595, 5629656551, 4548737594], "tags": {"highway": "tertiary", "oneway": "yes", "surface": "asphalt"}}, {"type": "way", "id": 458951095, "nodes": [4548737554, 4548738319, 4548738318, 4548738317], "tags": {"highway": "residential"}}, {"type": "way", "id": 458951099, "nodes": [4548738322, 4548737548, 4548737551], "tags": {"highway": "residential"}}, {"type": "way", "id": 458951101, "nodes": [4548737401, 4548738327, 4548738335], "tags": {"highway": "residential"}}, {"type": "way", "id": 458951149, "nodes": [4548737539, 4911050879, 4548737405, 4911050878, 4911050877, 4548737538, 4548737489, 4548737539], "tags": {"highway": "tertiary", "oneway": "yes", "surface": "asphalt"}}, {"type": "way", "id": 589541469, "nodes": [4548737453, 4548737452, 4548737595], "tags": {"highway": "residential", "oneway": "yes", "surface": "asphalt"}}, {"type": "way", "id": 589541470, "nodes": [4548737453, 5629656552, 4548738276], "tags": {"foot": "yes", "highway": "residential", "surface": "concrete"}}, {"type": "way", "id": 589541480, "nodes": [4548737594, 4235522204, 4548737581, 4548737580, 4548737586, 4548737585, 4548737584, 4548737583, 4548738309, 4548738308, 6128206800, 4548738307, 4548737591, 4548738304, 4548737076], "tags": {"highway": "tertiary", "surface": "asphalt"}}, {"type": "way", "id": 589541481, "nodes": [4548737488, 4548737487, 4548737486, 4548737668, 4548737404], "tags": {"highway": "tertiary", "oneway": "yes"}}, {"type": "way", "id": 589541482, "nodes": [4548737452, 4548737460, 4548737475, 4548737482, 4548737488], "tags": {"highway": "residential", "oneway": "yes"}}, {"type": "way", "id": 589541483, "nodes": [4548737595, 5629656554], "tags": {"highway": "residential", "surface": "asphalt"}}, {"type": "way", "id": 589541485, "nodes": [4548737538, 4548737560, 4548737482, 4548737481, 4548737480, 4548737479, 4548737478, 4548737477, 4548737476, 5629656548, 3782066942], "tags": {"highway": "residential"}}, {"type": "way", "id": 589541486, "nodes": [4911050879, 3782066930], "tags": {"highway": "residential"}}, {"type": "way", "id": 589541487, "nodes": [4548737469, 4548737470, 4548737471, 4548737472, 4548737473, 4548737474, 4548737475, 4548737561, 4548737537, 4548737534, 4548737532, 4548737529, 4548737520], "tags": {"highway": "residential", "lanes": "2", "oneway": "no", "surface": "asphalt"}}, {"type": "way", "id": 589541490, "nodes": [4548737536, 5629656554, 4548738258, 4548737564], "tags": {"highway": "residential"}}, {"type": "way", "id": 589541492, "nodes": [4548737536, 4548737535, 4548737531, 4548737530, 4548737519], "tags": {"highway": "residential", "lanes": "2", "oneway": "yes", "surface": "asphalt"}}, {"type": "way", "id": 589541494, "nodes": [4548737519, 12998447127, 4548738172], "tags": {"highway": "residential"}}, {"type": "way", "id": 589541497, "nodes": [4548737513, 11811908246, 4548737987, 4548737986, 4548737985, 4548737984, 4548737983, 4548737982, 6128206789, 4548737981, 4548737980, 11811908249, 4548737979, 11811908248, 4548737978], "tags": {"highway": "unclassified", "lanes": "2", "oneway": "no", "surface": "asphalt"}}, {"type": "way", "id": 589541521, "nodes": [4548737563, 4911050877], "tags": {"highway": "residential"}}, {"type": "way", "id": 589541524, "nodes": [4548737528, 4548737529, 4548737530, 4548738174], "tags": {"highway": "residential"}}, {"type": "way", "id": 589541526, "nodes": [4548737520, 4548737519], "tags": {"highway": "residential"}}, {"type": "way", "id": 589541528, "nodes": [4548737520, 4548737518, 4548737860, 9469152748, 9469152749, 4548737866], "tags": {"highway": "residential", "lanes": "2", "oneway": "no", "surface": "asphalt"}}, {"type": "way", "id": 589541530, "nodes": [4548737521, 4548737528], "tags": {"highway": "residential"}}, {"type": "way", "id": 595619654, "nodes": [4548738089, 5676291485, 5676291486, 5676291487, 5676291488, 5676291489, 5676291490, 5676291491, 5676291492, 5676291493, 5676291494, 5676291495, 5676291496, 5676291497, 5676291498, 5676291499, 5676291500, 5676291501, 5676291502, 5676291503, 5676291504, 5676291505, 5676291506, 5676291507, 5676291508, 5676291509, 5676291510, 5676291511, 5676291512, 5676291513], "tags": {"highway": "unclassified"}}, {"type": "way", "id": 653966724, "nodes": [4548737776, 4548737777], "tags": {"bridge": "yes", "highway": "tertiary", "layer": "1"}}, {"type": "way", "id": 1009489722, "nodes": [4548737871, 9469152736, 9314354865, 4548737512], "tags": {"highway": "residential", "surface": "asphalt"}}, {"type": "way", "id": 1009489723, "nodes": [4548737974, 4548737965, 4548737973], "tags": {"highway": "residential"}}, {"type": "way", "id": 1009489724, "nodes": [4548737905, 4548737904, 4548737877, 9469152744, 4548737902, 4548737901, 9469152742, 9469152743, 9469152741, 9469152740, 4548737900, 4548737899, 4548737975, 4548737969], "tags": {"highway": "residential", "surface": "asphalt"}}, {"type": "way", "id": 1009489725, "nodes": [4548737969, 9314354877], "tags": {"bridge": "yes", "highway": "residential", "layer": "1", "surface": "asphalt"}}, {"type": "way", "id": 1009489833, "nodes": [9314374460, 4548738226, 4548737523], "tags": {"highway": "residential"}}, {"type": "way", "id": 1009489834, "nodes": [9314374461, 9314374460], "tags": {"bridge": "yes", "highway": "residential", "layer": "1"}}, {"type": "way", "id": 1009489835, "nodes": [4548737876, 4548737875, 9469152733, 9314374463], "tags": {"highway": "residential", "surface": "asphalt"}}, {"type": "way", "id": 1009489836, "nodes": [9314374463, 9314374462], "tags": {"bridge": "yes", "highway": "residential", "layer": "1", "surface": "asphalt"}}, {"type": "way", "id": 1009489839, "nodes": [3745182525, 3745182526, 3745182527, 2186616794, 3745182528, 2186616793, 2186616796, 3745182529, 2186616802, 2186616810, 3745182530, 2186616812, 2186616815, 2186616817, 2186616814, 3745182531, 2186616816, 2186616818, 2186616821, 2186616823, 2186616824, 2186616825, 2186616826, 2186616827, 2186616831, 2186616836, 2186616839, 2186616841, 2186616843, 3745182537, 2186616844, 2186616845, 2186616842, 2186616840, 2186616837, 2186616835, 2186616834, 2186616833, 2186616832, 2186616828, 2186616822, 2186616820, 2186616813, 2186616811, 2186616809, 2186616808, 2186616807, 2186616803, 2186616801, 2186616795, 2186616791, 2186616787, 3745182538, 2186616790, 2186616786, 2186616783, 2186616776, 2186616773, 3745182539, 3745182540, 3745182541, 3745182542, 3745182543, 2186616767, 2186616770, 2186616768, 2186616763, 2186616760, 2186616755, 2186616753, 2186616750, 2186616745, 2186616744, 2186616741, 2186616739, 2186616738, 11811908237, 2186616735, 2186616728, 3745182544, 3745182545, 2186616717, 2186616719, 2186616727, 2186616726, 2186616720, 2186616714, 5732848327, 3745182546, 3745182547, 3745182548, 3745182549, 3745182550, 3745182591, 3745182592, 3745182551, 2186616709, 3745182552, 3745182553, 3745182593, 3745182554, 3745182555, 2186616705, 2186616704, 2186616703, 2186616699, 2186616702, 2186616698, 2186616697, 2186616694, 2186616693, 2186616692, 2186616690, 2186616691, 2186616689, 2186616688, 2186616687, 2186616686, 3745182556, 3745182557, 3745182558, 3745182559, 3745182560, 3745182561, 3745182562, 3745182563, 3745182564, 3745182565, 3745182566, 3745182567, 2186616665, 2186616683, 2186616666, 2186616652, 5676368220, 2186616642, 2186616629, 3745182583, 2186616621, 3745182594, 2186616615, 2186616614, 2186616620, 3745182595, 2186616623, 2186616631, 2186616638, 2186616653, 2186616658, 3745182584, 2186616657, 3745182585, 2186616651, 2186616636, 2186616628, 3745182596, 2186616627, 3745182586, 2186616632, 3745182587, 3745182588, 2186616640, 2186616647, 2186616659, 2186616668, 2186616675, 2186616673, 2186616656, 2186616641, 2186616633, 3745182589, 2186616622, 2186616613, 2186616606, 3745182590, 2186616588, 2186616587, 3745182597, 2186616591, 3745182598, 2186616601, 2186616600, 2186616589, 2186616599, 2186616597, 2186616585, 2186616575, 2186616567, 2186616552, 2186616543, 2186616542, 2186616549, 2186616568, 2186616576, 2186616583, 2186616593, 2186616596, 3745182615, 2186616592, 2186616582, 2186616574, 2186616569, 2186616554, 2186616532, 2186616523, 2186616518, 2186616519, 2186616525, 2186616526, 2186616521, 2186616511, 2186616503, 2186616496], "tags": {"highway": "secondary", "name": "Barbosa - Concepci\u00f3n", "oneway": "no", "source": "Gpx", "surface": "unpaved", "unsigned_ref": "62 AN 19"}}, {"type": "way", "id": 1085048175, "nodes": [4548737069, 4548737555, 4548737556, 4548737557, 4548737558, 4548737559], "tags": {"highway": "tertiary", "oneway": "yes", "surface": "asphalt"}}, {"type": "way", "id": 1272002866, "nodes": [4548737978, 4548737519], "tags": {"highway": "residential", "lanes": "2", "oneway": "no", "surface": "asphalt"}}, {"type": "way", "id": 1272002868, "nodes": [4548737466, 4548737467, 4548738274, 5629656545, 4548738273, 5629656541, 4548737468, 5629656550, 4548737469], "tags": {"highway": "residential", "lanes": "2", "oneway": "no", "surface": "asphalt"}}, {"type": "way", "id": 1272002869, "nodes": [4548737536, 4548737562, 4548737460, 4548737461, 4548737462, 4548737463, 4548737464, 4548737465, 4548737466], "tags": {"highway": "residential", "lanes": "2", "oneway": "no", "surface": "asphalt"}}, {"type": "way", "id": 1414558855, "nodes": [4548738001, 4548738000, 4548737999, 4548737998, 4548737997, 4548737996, 4548737995, 4548737994, 4548737993, 4548737992, 4548737991, 4548737990, 4548737989, 4548737988, 9924499187, 4548737513], "tags": {"description": "solo doble tracci\u00f3n", "highway": "unclassified", "lanes": "1", "name": "Rieles de Potrerito", "oneway": "no", "surface": "concrete:lanes"}}, {"type": "way", "id": 1414558912, "nodes": [12998451553, 4548737399, 4548737401, 4548737400, 1397149225, 4548737407, 3937925164, 4548737394, 1397149227, 4548737393, 4548737072], "tags": {"autor": "S.D.", "highway": "primary", "lanes": "2", "name": "Hatillo - Barbosa", "note": "V\u00eda vieja", "oneway": "no", "ref": "62", "source": "GPS", "surface": "asphalt"}}, {"type": "way", "id": 1414558917, "nodes": [336765604, 4548737078, 4548737077, 1397149185, 3474224970, 1397149194, 1397149177, 1397149173, 1397149165, 1397149020, 1397149019, 4548737076, 1397149011, 1397149013, 1397149007, 336765601, 6128206829, 1397149009], "tags": {"autor": "S.D.", "highway": "primary", "lanes": "2", "ref": "62", "source": "GPS", "surface": "asphalt"}}, {"type": "way", "id": 1414558919, "nodes": [4548738093, 4548738091, 4548738090], "tags": {"highway": "unclassified", "surface": "unpaved"}}, {"type": "way", "id": 1414558922, "nodes": [4548738086, 4548738085, 4548738084, 4548738083, 4548738082, 5638367177], "tags": {"highway": "unclassified", "surface": "unpaved"}}, {"type": "way", "id": 1414558923, "nodes": [4548738090, 4548738089, 4548738088, 4548738087, 4548738086], "tags": {"highway": "unclassified", "surface": "unpaved"}}]}